{
  "0xdc24316b9ae028f1497c275eb9192a3ea0f67022": {
    "graph": [
      {
        "date": "2023-06-10",
        "tokens": {
          "ETH": {
            "added": "2383.8232167684310167",
            "removed": "4347013.549570274338"
          },
          "stETH": {
            "added": "7675.6868985412104328",
            "removed": "1759189.2026000581627"
          }
        }
      },
      {
        "date": "2023-06-11",
        "tokens": {
          "ETH": {
            "added": "14204.755649158379034",
            "removed": "521865.25155944418468"
          },
          "stETH": {
            "added": "94467.726194755535877",
            "removed": "9151.9432186486026571"
          }
        }
      },
      {
        "date": "2023-06-12",
        "tokens": {
          "ETH": {
            "added": "4114.9334303204850639",
            "removed": "2056427.2593471645872"
          },
          "stETH": {
            "added": "132857.95121679988144",
            "removed": "2807357.4142516894733"
          }
        }
      },
      {
        "date": "2023-06-13",
        "tokens": {
          "ETH": {
            "added": "19987.084658494100218",
            "removed": "222240.08119471726452"
          },
          "stETH": {
            "added": "436290.55831769258802",
            "removed": "792591.12747292179489"
          }
        }
      },
      {
        "date": "2023-06-14",
        "tokens": {
          "ETH": { "added": "53344.062", "removed": "471304.82331267395978" },
          "stETH": {
            "added": "2939.2764387943144789",
            "removed": "38673.357279649477274"
          }
        }
      },
      {
        "date": "2023-06-15",
        "tokens": {
          "ETH": {
            "added": "41231.805945830956137",
            "removed": "898493.8300284280945"
          },
          "stETH": {
            "added": "33735.138933833036351",
            "removed": "1451421.5251322429511"
          }
        }
      },
      {
        "date": "2023-06-16",
        "tokens": {
          "ETH": {
            "added": "15343.20437511",
            "removed": "25200.298459960742196"
          },
          "stETH": {
            "added": "193767.52462385788785",
            "removed": "205275.5786374282512"
          }
        }
      },
      {
        "date": "2023-06-17",
        "tokens": {
          "ETH": { "added": "72345.705", "removed": "47664.458531027690609" },
          "stETH": {
            "added": "79292.83582440693634",
            "removed": "258233.19203634913888"
          }
        }
      }
    ],
    "tokensSummary": [
      {
        "symbol": "ETH",
        "totalAdded": "222955.37427568235147",
        "totalRemoved": "8590209.5520036908615",
        "tvlBefore": "473079456.95990556238",
        "tvlNow": "464712202.78217755387",
        "tvlPercentChange": "-0.017686784016151329455"
      },
      {
        "symbol": "stETH",
        "totalAdded": "981026.69844868139079",
        "totalRemoved": "7321893.340628987852",
        "tvlBefore": "470560450.80928757848",
        "tvlNow": "464219584.16710727202",
        "tvlPercentChange": "-0.013475137214092355816"
      }
    ]
  },
  "0xdcef968d416a41cdac0ed8702fac8128a64241a2": {
    "graph": [
      {
        "date": "2023-06-10",
        "tokens": {
          "FRAX": { "added": "0", "removed": "0" },
          "USDC": { "added": "0", "removed": "57628.351819443604049" }
        }
      },
      {
        "date": "2023-06-11",
        "tokens": {
          "FRAX": { "added": "0", "removed": "0" },
          "USDC": { "added": "0", "removed": "0" }
        }
      },
      {
        "date": "2023-06-12",
        "tokens": {
          "FRAX": { "added": "0", "removed": "0" },
          "USDC": { "added": "0", "removed": "299859.71755292902263" }
        }
      },
      {
        "date": "2023-06-13",
        "tokens": {
          "FRAX": {
            "added": "19.996345565850464065",
            "removed": "27.962434413164400894"
          },
          "USDC": { "added": "8.009952673312", "removed": "0" }
        }
      },
      {
        "date": "2023-06-14",
        "tokens": {
          "FRAX": {
            "added": "29.994249707862765623",
            "removed": "19.965774365128838781"
          },
          "USDC": { "added": "19.99936", "removed": "49998.4" }
        }
      },
      {
        "date": "2023-06-15",
        "tokens": {
          "FRAX": { "added": "1.0000896103964458279", "removed": "0" },
          "USDC": { "added": "0.342928025952", "removed": "0" }
        }
      }
    ],
    "tokensSummary": [
      {
        "symbol": "FRAX",
        "totalAdded": "50.990684884109675516",
        "totalRemoved": "47.928208778293239675",
        "tvlBefore": "443299527.57382794323",
        "tvlNow": "443299530.63630404905",
        "tvlPercentChange": "6.9083676280479893517e-9"
      },
      {
        "symbol": "USDC",
        "totalAdded": "28.352240699264",
        "totalRemoved": "407486.46937237262668",
        "tvlBefore": "164075405.3065722701",
        "tvlNow": "163667947.18944059674",
        "tvlPercentChange": "-0.0024833588944689448504"
      }
    ]
  },
  "0xbebc44782c7db0a1a60cb6fe97d0b483032ff1c7": {
    "graph": [
      {
        "date": "2023-06-10",
        "tokens": {
          "DAI": { "added": "0.099982", "removed": "823.44286280625494593" },
          "USDC": { "added": "0", "removed": "195949.3880230218419" },
          "USDT": { "added": "0", "removed": "741.02741600215506428" }
        }
      },
      {
        "date": "2023-06-11",
        "tokens": {
          "DAI": { "added": "0", "removed": "8977.8944612779762569" },
          "USDC": { "added": "0", "removed": "5432.9132363649738831" },
          "USDT": { "added": "0", "removed": "28342.175609905855298" }
        }
      },
      {
        "date": "2023-06-12",
        "tokens": {
          "DAI": {
            "added": "1.0000638675826683895",
            "removed": "377.86509088356215014"
          },
          "USDC": {
            "added": "1.00967268944",
            "removed": "1430638.1758991683058"
          },
          "USDT": {
            "added": "1486509.800066652543",
            "removed": "895.37162958763499183"
          }
        }
      },
      {
        "date": "2023-06-13",
        "tokens": {
          "DAI": {
            "added": "11.976881440585439411",
            "removed": "491.53792048971800527"
          },
          "USDC": {
            "added": "10.812477989632",
            "removed": "356584.50877871910878"
          },
          "USDT": {
            "added": "12.890612645706",
            "removed": "4226.7341436921158538"
          }
        }
      },
      {
        "date": "2023-06-14",
        "tokens": {
          "DAI": {
            "added": "183.29541539551186952",
            "removed": "1359.5312001808839957"
          },
          "USDC": {
            "added": "107.412311696032",
            "removed": "59112.509565600005646"
          },
          "USDT": {
            "added": "152.626565405538",
            "removed": "603.90813806962077344"
          }
        }
      },
      {
        "date": "2023-06-15",
        "tokens": {
          "DAI": { "added": "0.099982", "removed": "16525.917770717659163" },
          "USDC": { "added": "0.3999872", "removed": "625659.31086107410043" },
          "USDT": { "added": "0.0999393", "removed": "12194.438776408082394" }
        }
      },
      {
        "date": "2023-06-16",
        "tokens": {
          "DAI": { "added": "0", "removed": "77.523564090269325298" },
          "USDC": { "added": "329989.44", "removed": "3805912.9831916661638" },
          "USDT": {
            "added": "3574487.84805984",
            "removed": "33635.247021313476093"
          }
        }
      },
      {
        "date": "2023-06-17",
        "tokens": {
          "DAI": { "added": "0", "removed": "0" },
          "USDC": { "added": "0", "removed": "161.73350099951541684" },
          "USDT": { "added": "0", "removed": "679.24104597854896659" }
        }
      }
    ],
    "tokensSummary": [
      {
        "symbol": "DAI",
        "totalAdded": "196.47232470367997732",
        "totalRemoved": "28633.712870446323842",
        "tvlBefore": "76949618.038515357949",
        "tvlNow": "76921180.797969615305",
        "tvlPercentChange": "-0.00036955661731171996984"
      },
      {
        "symbol": "USDC",
        "totalAdded": "330109.074449575104",
        "totalRemoved": "6479451.5230566140157",
        "tvlBefore": "81341598.589126208032",
        "tvlNow": "75192256.14051916912",
        "tvlPercentChange": "-0.075598986930029262652"
      },
      {
        "symbol": "USDT",
        "totalAdded": "5061163.265243843787",
        "totalRemoved": "81318.143780957489435",
        "tvlBefore": "216089314.41193875315",
        "tvlNow": "221069159.53340163945",
        "tvlPercentChange": "0.02304530945926197098"
      }
    ]
  },
  "0xd51a44d3fae010294c616388b506acda1bfaae46": {
    "graph": [
      {
        "date": "2023-06-14",
        "tokens": {
          "USDT": { "added": "0", "removed": "0" },
          "WBTC": { "added": "0", "removed": "0" },
          "WETH": { "added": "0", "removed": "2242.1293452090689456" }
        }
      }
    ],
    "tokensSummary": [
      {
        "symbol": "USDT",
        "totalAdded": "0",
        "totalRemoved": "0",
        "tvlBefore": "56204082.100458580137",
        "tvlNow": "56204082.100458580137",
        "tvlPercentChange": "0"
      },
      {
        "symbol": "WBTC",
        "totalAdded": "0",
        "totalRemoved": "0",
        "tvlBefore": "55985729.0003748",
        "tvlNow": "55985729.0003748",
        "tvlPercentChange": "0"
      },
      {
        "symbol": "WETH",
        "totalAdded": "0",
        "totalRemoved": "2242.1293452090689456",
        "tvlBefore": "55881836.91986553219",
        "tvlNow": "55879594.790520323121",
        "tvlPercentChange": "-0.000040122685093982844857"
      }
    ]
  },
  "0xa1f8a6807c402e4a15ef4eba36528a3fed24e577": {
    "graph": [
      {
        "date": "2023-06-10",
        "tokens": {
          "ETH": { "added": "2.091924", "removed": "1277.6859014352929427" },
          "frxETH": { "added": "0", "removed": "9428.5322281739776169" }
        }
      },
      {
        "date": "2023-06-11",
        "tokens": {
          "ETH": { "added": "1752.3001386", "removed": "0" },
          "frxETH": { "added": "0", "removed": "1643.4869741945618239" }
        }
      },
      {
        "date": "2023-06-12",
        "tokens": {
          "ETH": {
            "added": "5232.79622151",
            "removed": "1792.3674029533319105"
          },
          "frxETH": {
            "added": "1391.3675166679384",
            "removed": "246.77660854422972687"
          }
        }
      },
      {
        "date": "2023-06-13",
        "tokens": {
          "ETH": {
            "added": "786741.69427674",
            "removed": "174.17794252826384448"
          },
          "frxETH": { "added": "0", "removed": "0" }
        }
      },
      {
        "date": "2023-06-14",
        "tokens": {
          "ETH": { "added": "4.881156", "removed": "0" },
          "frxETH": { "added": "0", "removed": "173920.9395834923" }
        }
      },
      {
        "date": "2023-06-15",
        "tokens": {
          "ETH": { "added": "69750.498951", "removed": "0" },
          "frxETH": { "added": "0", "removed": "17.391552404087594645" }
        }
      },
      {
        "date": "2023-06-16",
        "tokens": {
          "ETH": { "added": "198.91233681", "removed": "0" },
          "frxETH": {
            "added": "128.701495291784302",
            "removed": "67.865455320437897871"
          }
        }
      }
    ],
    "tokensSummary": [
      {
        "symbol": "ETH",
        "totalAdded": "863683.17500466",
        "totalRemoved": "3244.2312469168886977",
        "tvlBefore": "27572630.011323615971",
        "tvlNow": "28433068.955081359082",
        "tvlPercentChange": "0.031206270254392681828"
      },
      {
        "symbol": "frxETH",
        "totalAdded": "1520.069011959722702",
        "totalRemoved": "185324.99240212959466",
        "tvlBefore": "111110096.30389488718",
        "tvlNow": "110926291.38050471731",
        "tvlPercentChange": "-0.0016542594193010947484"
      }
    ]
  },
  "0xae34574ac03a15cd58a92dc79de7b1a0800f1ce3": {
    "graph": [
      {
        "date": "2023-06-11",
        "tokens": {
          "FRAX": { "added": "0", "removed": "0" },
          "USDP": { "added": "0", "removed": "199572.8428775730034" }
        }
      }
    ],
    "tokensSummary": [
      {
        "symbol": "FRAX",
        "totalAdded": "0",
        "totalRemoved": "0",
        "tvlBefore": "56148942.872473429124",
        "tvlNow": "56148942.872473429124",
        "tvlPercentChange": "0"
      },
      {
        "symbol": "USDP",
        "totalAdded": "0",
        "totalRemoved": "199572.8428775730034",
        "tvlBefore": "56486337.533788723782",
        "tvlNow": "56286764.690911150779",
        "tvlPercentChange": "-0.0035331170614167273019"
      }
    ]
  },
  "0x21e27a5e5513d6e65c4f830167390997aa84843a": {
    "graph": [
      {
        "date": "2023-06-10",
        "tokens": {
          "ETH": { "added": "3526.0993617308", "removed": "0" },
          "stETH": {
            "added": "3599.907225259653291",
            "removed": "7553.6605890098302342"
          }
        }
      },
      {
        "date": "2023-06-11",
        "tokens": {
          "ETH": { "added": "1371134.7661578471404", "removed": "0" },
          "stETH": {
            "added": "785818.07438233301537",
            "removed": "556710.22984963590915"
          }
        }
      },
      {
        "date": "2023-06-12",
        "tokens": {
          "ETH": {
            "added": "6480838.9671151",
            "removed": "243.76362991371037322"
          },
          "stETH": {
            "added": "942115.56480745531165",
            "removed": "6066.0909972525039808"
          }
        }
      },
      {
        "date": "2023-06-13",
        "tokens": {
          "ETH": {
            "added": "4342577.5610538241038",
            "removed": "562985.57435412017713"
          },
          "stETH": { "added": "3685603.9061527748156", "removed": "0" }
        }
      },
      {
        "date": "2023-06-14",
        "tokens": {
          "ETH": { "added": "12535255.204821764478", "removed": "0" },
          "stETH": {
            "added": "19784438.707818744779",
            "removed": "2980.5565785903014744"
          }
        }
      },
      {
        "date": "2023-06-15",
        "tokens": {
          "ETH": {
            "added": "1608843.9698672203257",
            "removed": "51.708294045266273876"
          },
          "stETH": { "added": "9482.0069455209990563", "removed": "0" }
        }
      },
      {
        "date": "2023-06-16",
        "tokens": {
          "ETH": {
            "added": "3242607.6416689576745",
            "removed": "46.965160599004751133"
          },
          "stETH": { "added": "9433.1186153613699576", "removed": "0" }
        }
      },
      {
        "date": "2023-06-17",
        "tokens": {
          "ETH": { "added": "93790.1787468", "removed": "0" },
          "stETH": { "added": "271919.78903393818673", "removed": "0" }
        }
      }
    ],
    "tokensSummary": [
      {
        "symbol": "ETH",
        "totalAdded": "29678574.388793244522",
        "totalRemoved": "563328.01143867815853",
        "tvlBefore": "-2180564.58055809827",
        "tvlNow": "26934681.796796468093",
        "tvlPercentChange": "13.352159636520716653"
      },
      {
        "symbol": "stETH",
        "totalAdded": "25492411.074981388131",
        "totalRemoved": "573310.53801448854484",
        "tvlBefore": "21522518.502828491053",
        "tvlNow": "46441619.039795390639",
        "tvlPercentChange": "1.1578152683986323189"
      }
    ]
  },
  "0xa5407eae9ba41422680e2e00537571bcc53efbfd": {
    "graph": [
      {
        "date": "2023-06-13",
        "tokens": {
          "DAI": { "added": "0", "removed": "0" },
          "USDC": { "added": "0", "removed": "0" },
          "USDT": { "added": "0", "removed": "0" },
          "sUSD": { "added": "0", "removed": "0" }
        }
      },
      {
        "date": "2023-06-15",
        "tokens": {
          "DAI": { "added": "0.8719478251275269748", "removed": "0" },
          "USDC": { "added": "0.859991479392", "removed": "0" },
          "USDT": { "added": "1.436264657841", "removed": "0" },
          "sUSD": { "added": "1.0106463677543303661", "removed": "0" }
        }
      },
      {
        "date": "2023-06-16",
        "tokens": {
          "DAI": { "added": "0", "removed": "0" },
          "USDC": { "added": "0", "removed": "0" },
          "USDT": { "added": "0", "removed": "0" },
          "sUSD": { "added": "0", "removed": "0" }
        }
      }
    ],
    "tokensSummary": [
      {
        "symbol": "DAI",
        "totalAdded": "0.8719478251275269748",
        "totalRemoved": "0",
        "tvlBefore": "10563410.961712927177",
        "tvlNow": "10563411.833660752305",
        "tvlPercentChange": "8.2544154372898493639e-8"
      },
      {
        "symbol": "USDC",
        "totalAdded": "0.859991479392",
        "totalRemoved": "0",
        "tvlBefore": "10810552.955814053472",
        "tvlNow": "10810553.815805532864",
        "tvlPercentChange": "7.9551109263979470817e-8"
      },
      {
        "symbol": "USDT",
        "totalAdded": "1.436264657841",
        "totalRemoved": "0",
        "tvlBefore": "13268973.981312759597",
        "tvlNow": "13268975.417577417438",
        "tvlPercentChange": "1.0824232980362689978e-7"
      },
      {
        "symbol": "sUSD",
        "totalAdded": "1.0106463677543303661",
        "totalRemoved": "0",
        "tvlBefore": "12115345.33710725945",
        "tvlNow": "12115346.347753627204",
        "tvlPercentChange": "8.3418700799106454396e-8"
      }
    ]
  },
  "0x971add32ea87f10bd192671630be3be8a11b8623": {
    "graph": [
      {
        "date": "2023-06-10",
        "tokens": {
          "CRV": {
            "added": "10750.995301551655721",
            "removed": "8608.7854447271668353"
          },
          "cvxCRV": {
            "added": "1819.3381131961394314",
            "removed": "895209.5218328402405"
          }
        }
      },
      {
        "date": "2023-06-11",
        "tokens": {
          "CRV": {
            "added": "4176.3950479154296559",
            "removed": "37704.97537321986"
          },
          "cvxCRV": {
            "added": "2834.249248634024084",
            "removed": "97540.166014624184613"
          }
        }
      },
      {
        "date": "2023-06-12",
        "tokens": {
          "CRV": { "added": "34587.231393274262579", "removed": "0" },
          "cvxCRV": {
            "added": "43500.943192988386413",
            "removed": "663.72684371136221422"
          }
        }
      },
      {
        "date": "2023-06-13",
        "tokens": {
          "CRV": { "added": "1526.4534562961880866", "removed": "0" },
          "cvxCRV": { "added": "549.31355168609760583", "removed": "0" }
        }
      },
      {
        "date": "2023-06-14",
        "tokens": {
          "CRV": {
            "added": "1758.2777538895788237",
            "removed": "299825.74238285124006"
          },
          "cvxCRV": { "added": "0", "removed": "0" }
        }
      },
      {
        "date": "2023-06-15",
        "tokens": {
          "CRV": {
            "added": "665161.91992711771411",
            "removed": "191494.82419030618906"
          },
          "cvxCRV": {
            "added": "636093.80832893200337",
            "removed": "114609.65981329233097"
          }
        }
      },
      {
        "date": "2023-06-16",
        "tokens": {
          "CRV": {
            "added": "47990.248074596235787",
            "removed": "2720.0202363850066068"
          },
          "cvxCRV": { "added": "3452.6203310201139269", "removed": "0" }
        }
      },
      {
        "date": "2023-06-17",
        "tokens": {
          "CRV": {
            "added": "30177.805456212735282",
            "removed": "11903.460725325509802"
          },
          "cvxCRV": { "added": "29500.232251166005118", "removed": "0" }
        }
      }
    ],
    "tokensSummary": [
      {
        "symbol": "CRV",
        "totalAdded": "796129.32641085380005",
        "totalRemoved": "552257.80835281497236",
        "tvlBefore": "13258717.830173218889",
        "tvlNow": "13502589.348231257717",
        "tvlPercentChange": "0.018393295730530888125"
      },
      {
        "symbol": "cvxCRV",
        "totalAdded": "717750.50501762276995",
        "totalRemoved": "1108023.0745044681183",
        "tvlBefore": "33236034.320347219478",
        "tvlNow": "32845761.75086037413",
        "tvlPercentChange": "-0.011742452957088177047"
      }
    ]
  },
  "0x8301ae4fc9c624d1d396cbdaa1ed877821d7c511": {
    "graph": [
      {
        "date": "2023-06-10",
        "tokens": {
          "WETH": { "added": "607.59854957353790914", "removed": "0" },
          "CRV": { "added": "594.57868697257657446", "removed": "0" }
        }
      },
      {
        "date": "2023-06-11",
        "tokens": {
          "WETH": { "added": "0.00174293", "removed": "7577.0259509500257729" },
          "CRV": { "added": "416.64896091788700288", "removed": "0" }
        }
      },
      {
        "date": "2023-06-12",
        "tokens": {
          "WETH": {
            "added": "532.79854475626571223",
            "removed": "358613.76781041688937"
          },
          "CRV": { "added": "672.521548288575111", "removed": "0" }
        }
      },
      {
        "date": "2023-06-13",
        "tokens": {
          "WETH": { "added": "0.174293", "removed": "384440.71047790445699" },
          "CRV": { "added": "0.6285208335939159", "removed": "0" }
        }
      },
      {
        "date": "2023-06-14",
        "tokens": {
          "WETH": { "added": "3485.86", "removed": "1863501.4581166031076" },
          "CRV": { "added": "73225.852886977522507", "removed": "0" }
        }
      },
      {
        "date": "2023-06-15",
        "tokens": {
          "WETH": {
            "added": "50545.144293",
            "removed": "3343307.4430635613986"
          },
          "CRV": {
            "added": "16349.199864440452882",
            "removed": "2891.19583453201314"
          }
        }
      },
      {
        "date": "2023-06-16",
        "tokens": {
          "WETH": { "added": "17.4467293", "removed": "0" },
          "CRV": { "added": "2852.0230152474756167", "removed": "0" }
        }
      },
      {
        "date": "2023-06-17",
        "tokens": {
          "WETH": { "added": "0", "removed": "0" },
          "CRV": { "added": "166.92162347295176611", "removed": "0" }
        }
      }
    ],
    "tokensSummary": [
      {
        "symbol": "WETH",
        "totalAdded": "55189.024152559803621",
        "totalRemoved": "5957440.4054194358783",
        "tvlBefore": "29025942.034746367521",
        "tvlNow": "23123690.653479491446",
        "tvlPercentChange": "-0.20334400772251975317"
      },
      {
        "symbol": "CRV",
        "totalAdded": "94278.375107151035376",
        "totalRemoved": "2891.19583453201314",
        "tvlBefore": "23069730.405944087451",
        "tvlNow": "23161117.585216706473",
        "tvlPercentChange": "0.0039613457836105634004"
      }
    ]
  },
  "0x960ea3e3c7fb317332d990873d354e18d7645590": {
    "graph": [
      {
        "date": "2023-06-10",
        "tokens": {
          "USDT": { "added": "0", "removed": "0" },
          "WBTC": { "added": "0", "removed": "0" },
          "WETH": { "added": "0", "removed": "78808.878604899281736" }
        }
      },
      {
        "date": "2023-06-11",
        "tokens": {
          "USDT": { "added": "0", "removed": "0" },
          "WBTC": { "added": "0", "removed": "0" },
          "WETH": { "added": "0", "removed": "49100.141325036658744" }
        }
      },
      {
        "date": "2023-06-12",
        "tokens": {
          "USDT": {
            "added": "96.796356684768",
            "removed": "0.012713073876263107931"
          },
          "WBTC": { "added": "0", "removed": "0" },
          "WETH": { "added": "0", "removed": "247.98800139153577594" }
        }
      },
      {
        "date": "2023-06-13",
        "tokens": {
          "USDT": { "added": "0", "removed": "0.01075919875103052404" },
          "WBTC": { "added": "0", "removed": "118184.22869641366729" },
          "WETH": {
            "added": "231.63728315097959893",
            "removed": "43.167419817648723621"
          }
        }
      },
      {
        "date": "2023-06-14",
        "tokens": {
          "USDT": { "added": "35.987328", "removed": "0.12281935865691339019" },
          "WBTC": { "added": "0", "removed": "0" },
          "WETH": {
            "added": "1160.4781045614565534",
            "removed": "16.695584917401746745"
          }
        }
      },
      {
        "date": "2023-06-15",
        "tokens": {
          "USDT": { "added": "0", "removed": "0.98938609739078231287" },
          "WBTC": { "added": "0", "removed": "0" },
          "WETH": { "added": "0", "removed": "307091.53458531416865" }
        }
      },
      {
        "date": "2023-06-16",
        "tokens": {
          "USDT": { "added": "251.616310871328", "removed": "0" },
          "WBTC": { "added": "255.2942835", "removed": "0" },
          "WETH": {
            "added": "259.24972140943065341",
            "removed": "97.533110612536927393"
          }
        }
      },
      {
        "date": "2023-06-17",
        "tokens": {
          "USDT": { "added": "0", "removed": "0" },
          "WBTC": { "added": "0", "removed": "0" },
          "WETH": { "added": "0", "removed": "17.316024177656511251" }
        }
      }
    ],
    "tokensSummary": [
      {
        "symbol": "USDT",
        "totalAdded": "384.399995556096",
        "totalRemoved": "1.135677728674989335",
        "tvlBefore": "14772438.926014882979",
        "tvlNow": "14772822.1903327104",
        "tvlPercentChange": "0.000025944552537799056443"
      },
      {
        "symbol": "WBTC",
        "totalAdded": "255.2942835",
        "totalRemoved": "118184.22869641366729",
        "tvlBefore": "14802967.592920603667",
        "tvlNow": "14685038.65850769",
        "tvlPercentChange": "-0.0079665738422147327165"
      },
      {
        "symbol": "WETH",
        "totalAdded": "1651.3651091218668057",
        "totalRemoved": "435423.25465616688881",
        "tvlBefore": "15087037.394985618738",
        "tvlNow": "14653265.505438573716",
        "tvlPercentChange": "-0.028751296771572594219"
      }
    ]
  },
  "0xc4c319e2d4d66cca4464c0c2b32c9bd23ebe784e": {
    "graph": [
      {
        "date": "2023-06-12",
        "tokens": {
          "ETH": { "added": "1.93981431", "removed": "0" },
          "alETH": { "added": "0", "removed": "0" }
        }
      },
      {
        "date": "2023-06-13",
        "tokens": {
          "ETH": { "added": "6.38064707", "removed": "0" },
          "alETH": { "added": "0", "removed": "0" }
        }
      },
      {
        "date": "2023-06-14",
        "tokens": {
          "ETH": { "added": "0", "removed": "0" },
          "alETH": { "added": "0", "removed": "0" }
        }
      },
      {
        "date": "2023-06-15",
        "tokens": {
          "ETH": { "added": "1.74287", "removed": "0" },
          "alETH": { "added": "0", "removed": "0" }
        }
      },
      {
        "date": "2023-06-16",
        "tokens": {
          "ETH": { "added": "0.00348574", "removed": "0" },
          "alETH": { "added": "0", "removed": "0" }
        }
      },
      {
        "date": "2023-06-17",
        "tokens": {
          "ETH": { "added": "0", "removed": "175629.29341150573168" },
          "alETH": { "added": "0", "removed": "0" }
        }
      }
    ],
    "tokensSummary": [
      {
        "symbol": "ETH",
        "totalAdded": "10.06681712",
        "totalRemoved": "175629.29341150573168",
        "tvlBefore": "13758220.333562433107",
        "tvlNow": "13582601.106968047375",
        "tvlPercentChange": "-0.012764676123551542744"
      },
      {
        "symbol": "alETH",
        "totalAdded": "0",
        "totalRemoved": "0",
        "tvlBefore": "28980113.692534840463",
        "tvlNow": "28980113.692534840463",
        "tvlPercentChange": "0"
      }
    ]
  },
  "0xa138341185a9d0429b0021a11fb717b225e13e1f": {
    "graph": [
      {
        "date": "2023-06-10",
        "tokens": {
          "USDR": { "added": "0", "removed": "0" },
          "am3CRV": { "added": "0", "removed": "1963.752280053618601" }
        }
      },
      {
        "date": "2023-06-11",
        "tokens": {
          "USDR": { "added": "651.79851316899410263", "removed": "0" },
          "am3CRV": { "added": "651.13710339640354893", "removed": "0" }
        }
      },
      {
        "date": "2023-06-15",
        "tokens": {
          "USDR": { "added": "0", "removed": "999.3384657444446" },
          "am3CRV": { "added": "0", "removed": "0" }
        }
      }
    ],
    "tokensSummary": [
      {
        "symbol": "USDR",
        "totalAdded": "651.79851316899410263",
        "totalRemoved": "999.3384657444446",
        "tvlBefore": "15703093.358184291446",
        "tvlNow": "15702745.818231715996",
        "tvlPercentChange": "-0.000022131942073331413763"
      },
      {
        "symbol": "am3CRV",
        "totalAdded": "651.13710339640354893",
        "totalRemoved": "1963.752280053618601",
        "tvlBefore": "17235908.04874312289",
        "tvlNow": "17234595.433566465675",
        "tvlPercentChange": "-0.000076155847022688981038"
      }
    ]
  },
  "0x445fe580ef8d70ff569ab36e80c647af338db351": {
    "graph": [
      {
        "date": "2023-06-10",
        "tokens": {
          "amDAI": { "added": "0", "removed": "0.47098857397319085576" },
          "amUSDC": { "added": "0", "removed": "2309.5921211100601813" },
          "amUSDT": { "added": "0", "removed": "0" }
        }
      },
      {
        "date": "2023-06-11",
        "tokens": {
          "amDAI": {
            "added": "2526.9298377881278671",
            "removed": "4158.9425217147809484"
          },
          "amUSDC": { "added": "0.999555", "removed": "2645.1336117922216743" },
          "amUSDT": { "added": "0", "removed": "0" }
        }
      },
      {
        "date": "2023-06-12",
        "tokens": {
          "amDAI": { "added": "0.84056866589584772436", "removed": "0" },
          "amUSDC": {
            "added": "0.14993325",
            "removed": "1178.6678059198104329"
          },
          "amUSDT": {
            "added": "0.099824958117",
            "removed": "386.86666195049967842"
          }
        }
      },
      {
        "date": "2023-06-13",
        "tokens": {
          "amDAI": {
            "added": "12.456794620148836024",
            "removed": "23.581005983501361016"
          },
          "amUSDC": {
            "added": "46.723995565335",
            "removed": "12916.221795508522593"
          },
          "amUSDT": {
            "added": "10.1433537492097338",
            "removed": "783.51330107706369548"
          }
        }
      },
      {
        "date": "2023-06-14",
        "tokens": {
          "amDAI": {
            "added": "1.0545006423984605954",
            "removed": "4.287181511251614387e-11"
          },
          "amUSDC": {
            "added": "1.0995105",
            "removed": "7317.7271410689795795"
          },
          "amUSDT": { "added": "0", "removed": "0.32838931952636756292" }
        }
      },
      {
        "date": "2023-06-15",
        "tokens": {
          "amDAI": { "added": "0", "removed": "75761.766577895092118" },
          "amUSDC": { "added": "0", "removed": "248.84378437200549404" },
          "amUSDT": {
            "added": "34476.3660999436794",
            "removed": "32287.604712098894208"
          }
        }
      },
      {
        "date": "2023-06-16",
        "tokens": {
          "amDAI": { "added": "0", "removed": "0" },
          "amUSDC": {
            "added": "4.00821555",
            "removed": "1127.883975196122998"
          },
          "amUSDT": { "added": "0", "removed": "1638.7224230494111591" }
        }
      },
      {
        "date": "2023-06-17",
        "tokens": {
          "amDAI": {
            "added": "0.019980737799028590779",
            "removed": "2.1042336700767557297"
          },
          "amUSDC": { "added": "0.00999555", "removed": "0" },
          "amUSDT": { "added": "0.0099824958117", "removed": "0" }
        }
      }
    ],
    "tokensSummary": [
      {
        "symbol": "amDAI",
        "totalAdded": "2541.30168245437004",
        "totalRemoved": "79946.865327837467246",
        "tvlBefore": "5936804.2565477647432",
        "tvlNow": "5859398.692902381646",
        "tvlPercentChange": "-0.013038254303232530424"
      },
      {
        "symbol": "amUSDC",
        "totalAdded": "52.991205415335",
        "totalRemoved": "27744.070234967722953",
        "tvlBefore": "6241217.130654296333",
        "tvlNow": "6213526.051624743945",
        "tvlPercentChange": "-0.0044368075088343226919"
      },
      {
        "symbol": "amUSDT",
        "totalAdded": "34486.619261146817834",
        "totalRemoved": "35097.035487495395109",
        "tvlBefore": "19625595.146018569212",
        "tvlNow": "19624984.729792220635",
        "tvlPercentChange": "-0.0000311030683047801337"
      }
    ]
  },
  "0x828b154032950c8ff7cf8085d841723db2696056": {
    "graph": [
      {
        "date": "2023-06-10",
        "tokens": {
          "WETH": { "added": "0.0174264", "removed": "0" },
          "stETH": { "added": "0", "removed": "6331.6213872923761254" }
        }
      },
      {
        "date": "2023-06-11",
        "tokens": {
          "WETH": { "added": "0.00174264", "removed": "0" },
          "stETH": { "added": "0.0017422109932675178", "removed": "0" }
        }
      },
      {
        "date": "2023-06-12",
        "tokens": {
          "WETH": { "added": "0.0174264", "removed": "0" },
          "stETH": { "added": "0", "removed": "93416.722953265771262" }
        }
      },
      {
        "date": "2023-06-13",
        "tokens": {
          "WETH": { "added": "1742.814264", "removed": "0" },
          "stETH": { "added": "1742.4575960349496419", "removed": "0" }
        }
      },
      {
        "date": "2023-06-14",
        "tokens": {
          "WETH": { "added": "1.045584", "removed": "0" },
          "stETH": { "added": "0", "removed": "6840.0755496730075436" }
        }
      },
      {
        "date": "2023-06-15",
        "tokens": {
          "WETH": { "added": "0.174264", "removed": "0" },
          "stETH": { "added": "0", "removed": "0" }
        }
      }
    ],
    "tokensSummary": [
      {
        "symbol": "WETH",
        "totalAdded": "1744.07070744",
        "totalRemoved": "0",
        "tvlBefore": "12135745.141530762697",
        "tvlNow": "12137489.212238202697",
        "tvlPercentChange": "0.0001437135245590703545"
      },
      {
        "symbol": "stETH",
        "totalAdded": "1742.4593382459429094",
        "totalRemoved": "106588.41989023115493",
        "tvlBefore": "18552039.171509708916",
        "tvlNow": "18447193.210957723704",
        "tvlPercentChange": "-0.0056514520901290854913"
      }
    ]
  },
  "0xc5424b857f758e906013f3555dad202e4bdb4567": {
    "graph": [
      {
        "date": "2023-06-10",
        "tokens": {
          "ETH": { "added": "2.091924", "removed": "182670.51453354705104" },
          "sETH": { "added": "0", "removed": "0" }
        }
      },
      {
        "date": "2023-06-11",
        "tokens": {
          "ETH": { "added": "2.0570586", "removed": "0" },
          "sETH": { "added": "0", "removed": "0" }
        }
      },
      {
        "date": "2023-06-12",
        "tokens": {
          "ETH": { "added": "1.60903821", "removed": "358413.77096518580427" },
          "sETH": { "added": "0", "removed": "0" }
        }
      },
      {
        "date": "2023-06-13",
        "tokens": {
          "ETH": { "added": "5.05722627", "removed": "86199.643510530265513" },
          "sETH": { "added": "0", "removed": "0" }
        }
      },
      {
        "date": "2023-06-14",
        "tokens": {
          "ETH": {
            "added": "26150.095962",
            "removed": "3422412.4542026034244"
          },
          "sETH": { "added": "0", "removed": "0" }
        }
      },
      {
        "date": "2023-06-15",
        "tokens": {
          "ETH": { "added": "2.266251", "removed": "0" },
          "sETH": { "added": "0", "removed": "0" }
        }
      },
      {
        "date": "2023-06-16",
        "tokens": {
          "ETH": { "added": "0.21093567", "removed": "0" },
          "sETH": { "added": "0", "removed": "0" }
        }
      },
      {
        "date": "2023-06-17",
        "tokens": {
          "ETH": { "added": "0", "removed": "0" },
          "sETH": { "added": "0", "removed": "0" }
        }
      }
    ],
    "tokensSummary": [
      {
        "symbol": "ETH",
        "totalAdded": "26163.38839575",
        "totalRemoved": "4049696.3832118665452",
        "tvlBefore": "17624245.135891657776",
        "tvlNow": "13600712.141075541231",
        "tvlPercentChange": "-0.22829533768922780204"
      },
      {
        "symbol": "sETH",
        "totalAdded": "0",
        "totalRemoved": "0",
        "tvlBefore": "16762381.642064400205",
        "tvlNow": "16762381.642064400205",
        "tvlPercentChange": "0"
      }
    ]
  },
  "0xb576491f1e6e5e62f1d8f26062ee822b40b0e0d4": {
    "graph": [
      {
        "date": "2023-06-10",
        "tokens": {
          "WETH": { "added": "0", "removed": "61963.11965808246475" },
          "CVX": { "added": "0", "removed": "0" }
        }
      },
      {
        "date": "2023-06-11",
        "tokens": {
          "WETH": { "added": "0", "removed": "416159.44389268951985" },
          "CVX": { "added": "0", "removed": "4.2918931277933259396" }
        }
      },
      {
        "date": "2023-06-12",
        "tokens": {
          "WETH": { "added": "0", "removed": "0" },
          "CVX": { "added": "0", "removed": "0" }
        }
      },
      {
        "date": "2023-06-14",
        "tokens": {
          "WETH": { "added": "0.174293", "removed": "63197.836811081670511" },
          "CVX": { "added": "12858.490770585719931", "removed": "0" }
        }
      },
      {
        "date": "2023-06-15",
        "tokens": {
          "WETH": { "added": "0", "removed": "0" },
          "CVX": { "added": "0", "removed": "0" }
        }
      },
      {
        "date": "2023-06-17",
        "tokens": {
          "WETH": { "added": "0.174293", "removed": "0" },
          "CVX": { "added": "0", "removed": "0" }
        }
      }
    ],
    "tokensSummary": [
      {
        "symbol": "WETH",
        "totalAdded": "0.348586",
        "totalRemoved": "541320.40036185365511",
        "tvlBefore": "13155572.810308104299",
        "tvlNow": "12614252.758532250644",
        "tvlPercentChange": "-0.041147585101858891018"
      },
      {
        "symbol": "CVX",
        "totalAdded": "12858.490770585719931",
        "totalRemoved": "4.2918931277933259396",
        "tvlBefore": "12738871.727688179445",
        "tvlNow": "12751725.926565637372",
        "tvlPercentChange": "0.0010090531683052496562"
      }
    ]
  },
  "0xdebf20617708857ebe4f679508e7b7863a8a8eee": {
    "graph": [
      {
        "date": "2023-06-14",
        "tokens": {
          "aDAI": { "added": "0.0999048", "removed": "0" },
          "aUSDC": { "added": "0.0990817", "removed": "0" },
          "aUSDT": { "added": "0.0999815", "removed": "0" }
        }
      },
      {
        "date": "2023-06-15",
        "tokens": {
          "aDAI": { "added": "0.99888419399379375572", "removed": "0" },
          "aUSDC": {
            "added": "1.157726068552",
            "removed": "34.097295027981365601"
          },
          "aUSDT": {
            "added": "5.177710946235",
            "removed": "444976.27607466863377"
          }
        }
      },
      {
        "date": "2023-06-16",
        "tokens": {
          "aDAI": { "added": "0", "removed": "1740.9976665955683913" },
          "aUSDC": { "added": "0", "removed": "0" },
          "aUSDT": { "added": "299989.397419440505", "removed": "0" }
        }
      }
    ],
    "tokensSummary": [
      {
        "symbol": "aDAI",
        "totalAdded": "1.0987889939937937557",
        "totalRemoved": "1740.9976665955683913",
        "tvlBefore": "3993295.7058989363091",
        "tvlNow": "3991555.8070213347345",
        "tvlPercentChange": "-0.00043570499300399381812"
      },
      {
        "symbol": "aUSDC",
        "totalAdded": "1.256807768552",
        "totalRemoved": "34.097295027981365601",
        "tvlBefore": "3934925.9254470054304",
        "tvlNow": "3934893.084959746001",
        "tvlPercentChange": "-0.000008345897198992059458"
      },
      {
        "symbol": "aUSDT",
        "totalAdded": "299994.67511188674",
        "totalRemoved": "444976.27607466863377",
        "tvlBefore": "13740316.384240446079",
        "tvlNow": "13595334.783277664185",
        "tvlPercentChange": "-0.01055154749777593009"
      }
    ]
  },
  "0x9848482da3ee3076165ce6497eda906e66bb85c5": {
    "graph": [
      {
        "date": "2023-06-11",
        "tokens": {
          "ETH": { "added": "0.1394296", "removed": "3556.740136321542461" },
          "pETH": { "added": "0", "removed": "0" }
        }
      },
      {
        "date": "2023-06-12",
        "tokens": {
          "ETH": { "added": "3051.24773761", "removed": "0" },
          "pETH": { "added": "18525.02832991014133", "removed": "0" }
        }
      },
      {
        "date": "2023-06-13",
        "tokens": {
          "ETH": { "added": "40089.6003122", "removed": "174287" },
          "pETH": { "added": "209605.42952761032718", "removed": "0" }
        }
      },
      {
        "date": "2023-06-14",
        "tokens": {
          "ETH": {
            "added": "1132.0147351526564735",
            "removed": "21428.949517002947511"
          },
          "pETH": { "added": "58220.105388684278659", "removed": "0" }
        }
      },
      {
        "date": "2023-06-15",
        "tokens": {
          "ETH": { "added": "3.9214575", "removed": "273964.5046741104741" },
          "pETH": { "added": "0", "removed": "20518.032549523198424" }
        }
      },
      {
        "date": "2023-06-16",
        "tokens": {
          "ETH": { "added": "0.00522861", "removed": "0" },
          "pETH": { "added": "13911.079286451651507", "removed": "0" }
        }
      },
      {
        "date": "2023-06-17",
        "tokens": {
          "ETH": { "added": "136875.3357909206", "removed": "0" },
          "pETH": { "added": "65222.848813563915106", "removed": "0" }
        }
      }
    ],
    "tokensSummary": [
      {
        "symbol": "ETH",
        "totalAdded": "181152.26469159325647",
        "totalRemoved": "473237.19432743496407",
        "tvlBefore": "10774135.837445551032",
        "tvlNow": "10482050.907809709324",
        "tvlPercentChange": "-0.027109824309129220217"
      },
      {
        "symbol": "pETH",
        "totalAdded": "365484.49134622031378",
        "totalRemoved": "20518.032549523198424",
        "tvlBefore": "9669530.8619510727116",
        "tvlNow": "10014497.320747769827",
        "tvlPercentChange": "0.035675614848504800863"
      }
    ]
  },
  "0x94b17476a93b3262d87b9a326965d1e91f9c13e7": {
    "graph": [
      {
        "date": "2023-06-10",
        "tokens": {
          "ETH": { "added": "0.348574", "removed": "0" },
          "OETH": { "added": "0", "removed": "0" }
        }
      },
      {
        "date": "2023-06-11",
        "tokens": {
          "ETH": { "added": "6971.6194296", "removed": "0" },
          "OETH": { "added": "0", "removed": "0" }
        }
      },
      {
        "date": "2023-06-12",
        "tokens": {
          "ETH": { "added": "3.50839731", "removed": "0" },
          "OETH": { "added": "0", "removed": "0" }
        }
      },
      {
        "date": "2023-06-13",
        "tokens": {
          "ETH": { "added": "4.8277499", "removed": "0" },
          "OETH": { "added": "0", "removed": "0" }
        }
      },
      {
        "date": "2023-06-15",
        "tokens": {
          "ETH": { "added": "429.36165985924820522", "removed": "0" },
          "OETH": { "added": "522.58393024933017583", "removed": "0" }
        }
      },
      {
        "date": "2023-06-16",
        "tokens": {
          "ETH": { "added": "2.27095961", "removed": "0" },
          "OETH": { "added": "0", "removed": "0" }
        }
      }
    ],
    "tokensSummary": [
      {
        "symbol": "ETH",
        "totalAdded": "7411.9367702792482052",
        "totalRemoved": "0",
        "tvlBefore": "8776197.950253975759",
        "tvlNow": "8783609.8870242550072",
        "tvlPercentChange": "0.00084454986228572396863"
      },
      {
        "symbol": "OETH",
        "totalAdded": "522.58393024933017583",
        "totalRemoved": "0",
        "tvlBefore": "9672119.5585623203328",
        "tvlNow": "9672642.142492569663",
        "tvlPercentChange": "0.000054029928712647957583"
      }
    ]
  },
  "0x7f90122bf0700f9e7e1f688fe926940e8839f353": {
    "graph": [
      {
        "date": "2023-06-10",
        "tokens": {
          "USDC": {
            "added": "992.3374788",
            "removed": "68852.428157774862364"
          },
          "USDT": {
            "added": "10202.502865415328",
            "removed": "14219.57072871419612"
          }
        }
      },
      {
        "date": "2023-06-11",
        "tokens": {
          "USDC": {
            "added": "8053.185420353411",
            "removed": "3207.808968108517507"
          },
          "USDT": {
            "added": "13693.339176352992",
            "removed": "5214.0915662983321208"
          }
        }
      },
      {
        "date": "2023-06-12",
        "tokens": {
          "USDC": { "added": "129.99181", "removed": "21763.361098152908655" },
          "USDT": {
            "added": "57229.692557734944",
            "removed": "101.78635177549244132"
          }
        }
      },
      {
        "date": "2023-06-13",
        "tokens": {
          "USDC": {
            "added": "15331.543638896019",
            "removed": "10296.014307429847438"
          },
          "USDT": { "added": "0", "removed": "110764.48895160082866" }
        }
      },
      {
        "date": "2023-06-14",
        "tokens": {
          "USDC": {
            "added": "1699.9928937",
            "removed": "108097.06027492838666"
          },
          "USDT": {
            "added": "148936.86576288",
            "removed": "12699.907371836790735"
          }
        }
      },
      {
        "date": "2023-06-15",
        "tokens": {
          "USDC": {
            "added": "8164.707229036806",
            "removed": "531124.89142556848291"
          },
          "USDT": {
            "added": "6997.217869021536",
            "removed": "732253.67258106428019"
          }
        }
      },
      {
        "date": "2023-06-16",
        "tokens": {
          "USDC": {
            "added": "0.570273070533",
            "removed": "17289.079914617368099"
          },
          "USDT": {
            "added": "193956.424412167872",
            "removed": "24873.1140734400779"
          }
        }
      },
      {
        "date": "2023-06-17",
        "tokens": {
          "USDC": {
            "added": "1.739572400034",
            "removed": "1.0095259990284932589"
          },
          "USDT": {
            "added": "33973.63960290768",
            "removed": "54527.230042736557127"
          }
        }
      }
    ],
    "tokensSummary": [
      {
        "symbol": "USDC",
        "totalAdded": "34374.068316256803",
        "totalRemoved": "760631.65367257940213",
        "tvlBefore": "5610714.5895154293051",
        "tvlNow": "4884457.004159106706",
        "tvlPercentChange": "-0.12944119216355398458"
      },
      {
        "symbol": "USDT",
        "totalAdded": "464989.682246480352",
        "totalRemoved": "954653.86166746655529",
        "tvlBefore": "13566800.015145822715",
        "tvlNow": "13077135.835724836512",
        "tvlPercentChange": "-0.036092827997341350125"
      }
    ]
  },
  "0xb90b9b1f91a01ea22a182cd84c1e22222e39b415": {
    "graph": [
      {
        "date": "2023-06-10",
        "tokens": {
          "ETH": {
            "added": "16187.434864435704491",
            "removed": "96547.686341480219538"
          },
          "wstETH": {
            "added": "12838.104294200107613",
            "removed": "85.071610237084149239"
          }
        }
      },
      {
        "date": "2023-06-11",
        "tokens": {
          "ETH": {
            "added": "2145.1921687451255024",
            "removed": "34888.893542451833211"
          },
          "wstETH": { "added": "0", "removed": "1965.472412028478" }
        }
      },
      {
        "date": "2023-06-12",
        "tokens": {
          "ETH": {
            "added": "16448.106011286378922",
            "removed": "43783.04817171555826"
          },
          "wstETH": {
            "added": "12816.360833523773319",
            "removed": "20380.911221701204551"
          }
        }
      },
      {
        "date": "2023-06-13",
        "tokens": {
          "ETH": {
            "added": "7472.5868296967047659",
            "removed": "38253.676832052438851"
          },
          "wstETH": {
            "added": "95.959802003132536226",
            "removed": "2081.3370107175567781"
          }
        }
      },
      {
        "date": "2023-06-14",
        "tokens": {
          "ETH": {
            "added": "14745.063821375662889",
            "removed": "9570.0220621302445823"
          },
          "wstETH": { "added": "25216.130054526623165", "removed": "0" }
        }
      },
      {
        "date": "2023-06-15",
        "tokens": {
          "ETH": {
            "added": "1132.2031303303587374",
            "removed": "113179.92552479182014"
          },
          "wstETH": { "added": "13747.240894162329317", "removed": "0" }
        }
      },
      {
        "date": "2023-06-16",
        "tokens": {
          "ETH": {
            "added": "21264.402052333378912",
            "removed": "363.89076599420364309"
          },
          "wstETH": { "added": "2442.929567599048946", "removed": "0" }
        }
      },
      {
        "date": "2023-06-17",
        "tokens": {
          "ETH": { "added": "84688.938880622127628", "removed": "0" },
          "wstETH": { "added": "99272.196756956054635", "removed": "0" }
        }
      }
    ],
    "tokensSummary": [
      {
        "symbol": "ETH",
        "totalAdded": "164083.92775882544185",
        "totalRemoved": "336587.14324061631823",
        "tvlBefore": "8807089.5249245511831",
        "tvlNow": "8634586.3094427603067",
        "tvlPercentChange": "-0.019586858404651981972"
      },
      {
        "symbol": "wstETH",
        "totalAdded": "166428.92220297106953",
        "totalRemoved": "24512.792254684323478",
        "tvlBefore": "8739610.8589141425508",
        "tvlNow": "8881526.9888624292968",
        "tvlPercentChange": "0.016238266467383559067"
      }
    ]
  },
  "0x061b87122ed14b9526a813209c8a59a633257bab": {
    "graph": [
      {
        "date": "2023-06-10",
        "tokens": {
          "sUSD": { "added": "0", "removed": "2.8794228956912323871" },
          "3CRV": { "added": "0", "removed": "0" }
        }
      },
      {
        "date": "2023-06-14",
        "tokens": {
          "sUSD": { "added": "0", "removed": "279.85787229674434141" },
          "3CRV": { "added": "0", "removed": "0" }
        }
      },
      {
        "date": "2023-06-15",
        "tokens": {
          "sUSD": {
            "added": "0.0001507955646431744414",
            "removed": "1348.17226667738739"
          },
          "3CRV": { "added": "0", "removed": "0" }
        }
      },
      {
        "date": "2023-06-16",
        "tokens": {
          "sUSD": { "added": "0.099930081697189530792", "removed": "0" },
          "3CRV": { "added": "0", "removed": "0" }
        }
      }
    ],
    "tokensSummary": [
      {
        "symbol": "sUSD",
        "totalAdded": "0.10008087726183270523",
        "totalRemoved": "1630.9095618698229638",
        "tvlBefore": "8990922.431464471875",
        "tvlNow": "8989291.6219834793139",
        "tvlPercentChange": "-0.0001813840007433952839"
      },
      {
        "symbol": "3CRV",
        "totalAdded": "0",
        "totalRemoved": "0",
        "tvlBefore": "7605481.5808564464341",
        "tvlNow": "7605481.5808564464341",
        "tvlPercentChange": "0"
      }
    ]
  },
  "0x98a7f18d4e56cfe84e3d081b40001b3d5bd3eb8b": {
    "graph": [
      {
        "date": "2023-06-12",
        "tokens": {
          "USDC": { "added": "0", "removed": "3024.8554646937249733" },
          "EURS": { "added": "0", "removed": "0" }
        }
      }
    ],
    "tokensSummary": [
      {
        "symbol": "USDC",
        "totalAdded": "0",
        "totalRemoved": "3024.8554646937249733",
        "tvlBefore": "7510580.717707118749",
        "tvlNow": "7507555.862242425024",
        "tvlPercentChange": "-0.00040274588322608075033"
      },
      {
        "symbol": "EURS",
        "totalAdded": "0",
        "totalRemoved": "0",
        "tvlBefore": "7864945.25183",
        "tvlNow": "7864945.25183",
        "tvlPercentChange": "0"
      }
    ]
  },
  "0xf253f83aca21aabd2a20553ae0bf7f65c755a07f": {
    "graph": [
      {
        "date": "2023-06-10",
        "tokens": {
          "WBTC": {
            "added": "37282.8501999",
            "removed": "2659.1299089906743514"
          },
          "sBTC": { "added": "0", "removed": "0" }
        }
      },
      {
        "date": "2023-06-16",
        "tokens": {
          "WBTC": { "added": "26595", "removed": "0" },
          "sBTC": { "added": "0", "removed": "0" }
        }
      }
    ],
    "tokensSummary": [
      {
        "symbol": "WBTC",
        "totalAdded": "63877.8501999",
        "totalRemoved": "2659.1299089906743514",
        "tvlBefore": "6719704.0593527406744",
        "tvlNow": "6780922.77964365",
        "tvlPercentChange": "0.0091103298225913347048"
      },
      {
        "symbol": "sBTC",
        "totalAdded": "0",
        "totalRemoved": "0",
        "tvlBefore": "7339017.2884710191042",
        "tvlNow": "7339017.2884710191042",
        "tvlPercentChange": "0"
      }
    ]
  },
  "0xe57180685e3348589e9521aa53af0bcd497e884d": {
    "graph": [
      {
        "date": "2023-06-11",
        "tokens": {
          "DOLA": { "added": "0", "removed": "0" },
          "FRAXBP": { "added": "153533.9331044941586", "removed": "0" }
        }
      }
    ],
    "tokensSummary": [
      {
        "symbol": "DOLA",
        "totalAdded": "0",
        "totalRemoved": "0",
        "tvlBefore": "8327573.0168403299878",
        "tvlNow": "8327573.0168403299878",
        "tvlPercentChange": "0"
      },
      {
        "symbol": "FRAXBP",
        "totalAdded": "153533.9331044941586",
        "totalRemoved": "0",
        "tvlBefore": "3544097.6543791189833",
        "tvlNow": "3697631.5874836131419",
        "tvlPercentChange": "0.043321022183117964592"
      }
    ]
  },
  "0x4d9f9d15101eec665f77210cb999639f760f831e": {
    "graph": [
      {
        "date": "2023-06-10",
        "tokens": {
          "stETH": { "added": "0", "removed": "25018.149863321555608" },
          "frxETH": { "added": "0", "removed": "0" }
        }
      },
      {
        "date": "2023-06-11",
        "tokens": {
          "stETH": { "added": "0", "removed": "0" },
          "frxETH": { "added": "0", "removed": "128123.27133283049536" }
        }
      },
      {
        "date": "2023-06-12",
        "tokens": {
          "stETH": { "added": "766624.76687187259563", "removed": "0" },
          "frxETH": { "added": "765743.57520952209407", "removed": "0" }
        }
      },
      {
        "date": "2023-06-13",
        "tokens": {
          "stETH": { "added": "0", "removed": "69345.744387342134097" },
          "frxETH": { "added": "0", "removed": "0" }
        }
      },
      {
        "date": "2023-06-16",
        "tokens": {
          "stETH": { "added": "949504.991330797201", "removed": "0" },
          "frxETH": { "added": "0", "removed": "0" }
        }
      },
      {
        "date": "2023-06-17",
        "tokens": {
          "stETH": { "added": "0", "removed": "0" },
          "frxETH": { "added": "0", "removed": "139104.845564920144" }
        }
      }
    ],
    "tokensSummary": [
      {
        "symbol": "stETH",
        "totalAdded": "1716129.7582026697966",
        "totalRemoved": "94363.894250663689705",
        "tvlBefore": "2765021.3977254000725",
        "tvlNow": "4386787.2616774061794",
        "tvlPercentChange": "0.5865292273275445336"
      },
      {
        "symbol": "frxETH",
        "totalAdded": "765743.57520952209407",
        "totalRemoved": "267228.11689775063936",
        "tvlBefore": "5404228.1456359873873",
        "tvlNow": "5902743.603947758842",
        "tvlPercentChange": "0.092245450206304070058"
      }
    ]
  }
}
