{
  "0xdc24316b9ae028f1497c275eb9192a3ea0f67022": {
    "graph": [
      {
        "date": "2023-07-02",
        "tokens": {
          "ETH": {
            "added": "565920.09423936504118",
            "removed": "652058.61032524047765"
          },
          "stETH": {
            "added": "603236.22908909374023",
            "removed": "195374.35596738361769"
          }
        }
      },
      {
        "date": "2023-07-03",
        "tokens": {
          "ETH": {
            "added": "64975.942887902911868",
            "removed": "250563.56135395841531"
          },
          "stETH": {
            "added": "70114.183841441469739",
            "removed": "6511200.0898883276127"
          }
        }
      },
      {
        "date": "2023-07-04",
        "tokens": {
          "ETH": {
            "added": "24571.544622606194042",
            "removed": "441274.58489556067024"
          },
          "stETH": {
            "added": "7737.7443677495258746",
            "removed": "900348.80233936655411"
          }
        }
      },
      {
        "date": "2023-07-05",
        "tokens": {
          "ETH": {
            "added": "2770.9060368298363885",
            "removed": "119982.2432944984837"
          },
          "stETH": {
            "added": "4874.9294649238844636",
            "removed": "558284.27359225774108"
          }
        }
      },
      {
        "date": "2023-07-06",
        "tokens": {
          "ETH": {
            "added": "930.27482180701549839",
            "removed": "649620.37969328794916"
          },
          "stETH": {
            "added": "24966.887331171270732",
            "removed": "262605.46217555161188"
          }
        }
      },
      {
        "date": "2023-07-07",
        "tokens": {
          "ETH": { "added": "3773.0166", "removed": "168266.40441366650864" },
          "stETH": {
            "added": "14376.808258067234304",
            "removed": "544165.04866263529774"
          }
        }
      },
      {
        "date": "2023-07-08",
        "tokens": {
          "ETH": {
            "added": "620287.66801750597262",
            "removed": "8222288.9642432593628"
          },
          "stETH": {
            "added": "535647.79690459235067",
            "removed": "291837.51336588654391"
          }
        }
      },
      {
        "date": "2023-07-09",
        "tokens": {
          "ETH": {
            "added": "26.871117569176967985",
            "removed": "22314.750482362246823"
          },
          "stETH": {
            "added": "2907.9939280207583759",
            "removed": "267831.52465542786091"
          }
        }
      }
    ],
    "tokensSummary": [
      {
        "symbol": "ETH",
        "totalAdded": "1283256.3183435861486",
        "totalRemoved": "10526369.498701834114",
        "tvlBefore": "377829094.23122772295",
        "tvlNow": "368585981.05086947498",
        "tvlPercentChange": "-0.024463741203321819353"
      },
      {
        "symbol": "stETH",
        "totalAdded": "1263862.5731850602344",
        "totalRemoved": "9531647.07064683684",
        "tvlBefore": "379317691.19039482211",
        "tvlNow": "371049906.6929330455",
        "tvlPercentChange": "-0.021796464255372267031"
      }
    ]
  },
  "0xdcef968d416a41cdac0ed8702fac8128a64241a2": {
    "graph": [
      {
        "date": "2023-07-07",
        "tokens": {
          "FRAX": { "added": "0", "removed": "0" },
          "USDC": { "added": "0", "removed": "1168337.8876335883725" }
        }
      },
      {
        "date": "2023-07-08",
        "tokens": {
          "FRAX": { "added": "0", "removed": "0" },
          "USDC": { "added": "106097.7091220046", "removed": "0" }
        }
      }
    ],
    "tokensSummary": [
      {
        "symbol": "FRAX",
        "totalAdded": "0",
        "totalRemoved": "0",
        "tvlBefore": "431154798.57856293262",
        "tvlNow": "431154798.57856293262",
        "tvlPercentChange": "0"
      },
      {
        "symbol": "USDC",
        "totalAdded": "106097.7091220046",
        "totalRemoved": "1168337.8876335883725",
        "tvlBefore": "193253275.46800607117",
        "tvlNow": "192191035.2894944874",
        "tvlPercentChange": "-0.0054966218602977433032"
      }
    ]
  },
  "0xbebc44782c7db0a1a60cb6fe97d0b483032ff1c7": {
    "graph": [
      {
        "date": "2023-07-02",
        "tokens": {
          "DAI": { "added": "0", "removed": "0" },
          "USDC": {
            "added": "50031.3214814886",
            "removed": "20893.512243170772211"
          },
          "USDT": { "added": "0", "removed": "418.8350201867365935" }
        }
      },
      {
        "date": "2023-07-03",
        "tokens": {
          "DAI": {
            "added": "999737.52884302244609",
            "removed": "1928.4759154388872391"
          },
          "USDC": { "added": "500049.99", "removed": "0" },
          "USDT": { "added": "0", "removed": "55585.393806344862848" }
        }
      },
      {
        "date": "2023-07-04",
        "tokens": {
          "DAI": { "added": "0.999735", "removed": "14321.464693545863782" },
          "USDC": { "added": "9.999", "removed": "1062.5059791877821135" },
          "USDT": {
            "added": "2771131.300425",
            "removed": "149.41790176164518429"
          }
        }
      },
      {
        "date": "2023-07-06",
        "tokens": {
          "DAI": {
            "added": "24559.9933365831",
            "removed": "0.01150910143218626373"
          },
          "USDC": {
            "added": "26837.39469213",
            "removed": "298646.14006241295976"
          },
          "USDT": { "added": "25423.2957", "removed": "108137.08422903993236" }
        }
      },
      {
        "date": "2023-07-07",
        "tokens": {
          "DAI": { "added": "0", "removed": "590.21088252130817612" },
          "USDC": { "added": "0", "removed": "3944387.1421937946482" },
          "USDT": { "added": "3977764.32", "removed": "583.04126443142123961" }
        }
      },
      {
        "date": "2023-07-08",
        "tokens": {
          "DAI": { "added": "0", "removed": "4767.5209196460634574" },
          "USDC": { "added": "0", "removed": "157888.3059287105388" },
          "USDT": { "added": "0", "removed": "2045.759712363834373" }
        }
      },
      {
        "date": "2023-07-09",
        "tokens": {
          "DAI": { "added": "0", "removed": "171.49685637821414441" },
          "USDC": { "added": "0", "removed": "355.99264072883517093" },
          "USDT": { "added": "0", "removed": "816.75859265131540432" }
        }
      }
    ],
    "tokensSummary": [
      {
        "symbol": "DAI",
        "totalAdded": "1024298.5219146055461",
        "totalRemoved": "21779.180776631768985",
        "tvlBefore": "99495660.336687813343",
        "tvlNow": "100498179.67782578712",
        "tvlPercentChange": "0.01007601072997057115"
      },
      {
        "symbol": "USDC",
        "totalAdded": "576928.7051736186",
        "totalRemoved": "4423233.5990480055363",
        "tvlBefore": "116056085.05483126864",
        "tvlNow": "112209780.1609568817",
        "tvlPercentChange": "-0.033141777030107307691"
      },
      {
        "symbol": "USDT",
        "totalAdded": "6774318.916125",
        "totalRemoved": "167736.290526779748",
        "tvlBefore": "88548719.986795779748",
        "tvlNow": "95155302.612394",
        "tvlPercentChange": "0.074609577942892698529"
      }
    ]
  },
  "0xd632f22692fac7611d2aa1c0d552930d43caed3b": {
    "graph": [
      {
        "date": "2023-07-02",
        "tokens": {
          "FRAX": { "added": "0", "removed": "0.2967328581476914961" },
          "3Crv": { "added": "0", "removed": "0" }
        }
      },
      {
        "date": "2023-07-06",
        "tokens": {
          "FRAX": { "added": "0", "removed": "0" },
          "3Crv": { "added": "0", "removed": "427.27496012950454754" }
        }
      },
      {
        "date": "2023-07-08",
        "tokens": {
          "FRAX": { "added": "0", "removed": "0" },
          "3Crv": { "added": "0", "removed": "0" }
        }
      }
    ],
    "tokensSummary": [
      {
        "symbol": "FRAX",
        "totalAdded": "0",
        "totalRemoved": "0.2967328581476914961",
        "tvlBefore": "118513690.58372957051",
        "tvlNow": "118513690.28699671236",
        "tvlPercentChange": "-2.5037854840944229711e-9"
      },
      {
        "symbol": "3Crv",
        "totalAdded": "0",
        "totalRemoved": "427.27496012950454754",
        "tvlBefore": "51262692.663025334386",
        "tvlNow": "51262265.388065204881",
        "tvlPercentChange": "-0.0000083350081303413298558"
      }
    ]
  },
  "0xa1f8a6807c402e4a15ef4eba36528a3fed24e577": {
    "graph": [
      {
        "date": "2023-07-02",
        "tokens": {
          "ETH": { "added": "8685.4281783", "removed": "0" },
          "frxETH": { "added": "0", "removed": "0" }
        }
      },
      {
        "date": "2023-07-03",
        "tokens": {
          "ETH": { "added": "0", "removed": "811.11495043981070412" },
          "frxETH": { "added": "0", "removed": "15846.495454082107728" }
        }
      },
      {
        "date": "2023-07-04",
        "tokens": {
          "ETH": {
            "added": "326870.436783",
            "removed": "635171.07148545642755"
          },
          "frxETH": { "added": "0", "removed": "31715.498332267867934" }
        }
      },
      {
        "date": "2023-07-07",
        "tokens": {
          "ETH": { "added": "683188.15594569536977", "removed": "0" },
          "frxETH": { "added": "195.74057075681771261", "removed": "0" }
        }
      },
      {
        "date": "2023-07-09",
        "tokens": {
          "ETH": { "added": "0.0373566", "removed": "0" },
          "frxETH": { "added": "0", "removed": "0" }
        }
      }
    ],
    "tokensSummary": [
      {
        "symbol": "ETH",
        "totalAdded": "1018744.0582635953698",
        "totalRemoved": "635982.18643589623825",
        "tvlBefore": "54912255.007282670485",
        "tvlNow": "55295016.879110369617",
        "tvlPercentChange": "0.0069704271255466709226"
      },
      {
        "symbol": "frxETH",
        "totalAdded": "195.74057075681771261",
        "totalRemoved": "47561.993786349975662",
        "tvlBefore": "109485172.22078228473",
        "tvlNow": "109437805.96756669157",
        "tvlPercentChange": "-0.0004326271060712838729"
      }
    ]
  },
  "0xd51a44d3fae010294c616388b506acda1bfaae46": {
    "graph": [
      {
        "date": "2023-07-02",
        "tokens": {
          "USDT": { "added": "0", "removed": "0" },
          "WBTC": { "added": "0", "removed": "0" },
          "WETH": { "added": "0", "removed": "941.71556947895517936" }
        }
      }
    ],
    "tokensSummary": [
      {
        "symbol": "USDT",
        "totalAdded": "0",
        "totalRemoved": "0",
        "tvlBefore": "46065070.929628",
        "tvlNow": "46065070.929628",
        "tvlPercentChange": "0"
      },
      {
        "symbol": "WBTC",
        "totalAdded": "0",
        "totalRemoved": "0",
        "tvlBefore": "46113395.28712684",
        "tvlNow": "46113395.28712684",
        "tvlPercentChange": "0"
      },
      {
        "symbol": "WETH",
        "totalAdded": "0",
        "totalRemoved": "941.71556947895517936",
        "tvlBefore": "45917839.26412265265",
        "tvlNow": "45916897.548553173695",
        "tvlPercentChange": "-0.000020508708261774700928"
      }
    ]
  },
  "0x5a6a4d54456819380173272a5e8e9b9904bdf41b": {
    "graph": [
      {
        "date": "2023-07-05",
        "tokens": {
          "MIM": { "added": "0", "removed": "0" },
          "3Crv": { "added": "0", "removed": "406058.65213709647049" }
        }
      }
    ],
    "tokensSummary": [
      {
        "symbol": "MIM",
        "totalAdded": "0",
        "totalRemoved": "0",
        "tvlBefore": "69811376.762883561783",
        "tvlNow": "69811376.762883561783",
        "tvlPercentChange": "0"
      },
      {
        "symbol": "3Crv",
        "totalAdded": "0",
        "totalRemoved": "406058.65213709647049",
        "tvlBefore": "9451449.0841495181539",
        "tvlNow": "9045390.4320124216834",
        "tvlPercentChange": "-0.042962581559908531865"
      }
    ]
  },
  "0x21e27a5e5513d6e65c4f830167390997aa84843a": {
    "graph": [
      {
        "date": "2023-07-02",
        "tokens": {
          "ETH": { "added": "3175.3296783", "removed": "0" },
          "stETH": { "added": "0", "removed": "0" }
        }
      },
      {
        "date": "2023-07-03",
        "tokens": {
          "ETH": { "added": "0", "removed": "130.47101375486564301" },
          "stETH": { "added": "0", "removed": "0" }
        }
      },
      {
        "date": "2023-07-04",
        "tokens": {
          "ETH": { "added": "432942.52750569748183", "removed": "3735.66" },
          "stETH": {
            "added": "440638.1605363975914",
            "removed": "204989.44482959327656"
          }
        }
      },
      {
        "date": "2023-07-06",
        "tokens": {
          "ETH": { "added": "0", "removed": "1494.264" },
          "stETH": { "added": "0", "removed": "0" }
        }
      },
      {
        "date": "2023-07-08",
        "tokens": {
          "ETH": { "added": "0", "removed": "2521.5705" },
          "stETH": { "added": "953.35503269312575467", "removed": "0" }
        }
      }
    ],
    "tokensSummary": [
      {
        "symbol": "ETH",
        "totalAdded": "436117.85718399748183",
        "totalRemoved": "7881.965513754865643",
        "tvlBefore": "29467151.406883059174",
        "tvlNow": "29895387.29855330179",
        "tvlPercentChange": "0.014532653182425142872"
      },
      {
        "symbol": "stETH",
        "totalAdded": "441591.51556909071715",
        "totalRemoved": "204989.44482959327656",
        "tvlBefore": "47097238.150483125005",
        "tvlNow": "47333840.221222622446",
        "tvlPercentChange": "0.0050236931087873221551"
      }
    ]
  },
  "0x971add32ea87f10bd192671630be3be8a11b8623": {
    "graph": [
      {
        "date": "2023-07-02",
        "tokens": {
          "CRV": { "added": "38896.170434503769871", "removed": "0" },
          "cvxCRV": { "added": "272.67315927578259213", "removed": "0" }
        }
      },
      {
        "date": "2023-07-03",
        "tokens": {
          "CRV": { "added": "61576.932573711733582", "removed": "0" },
          "cvxCRV": { "added": "0", "removed": "0" }
        }
      },
      {
        "date": "2023-07-04",
        "tokens": {
          "CRV": { "added": "3107.5529974375789429", "removed": "0" },
          "cvxCRV": { "added": "341228.2183565247238", "removed": "0" }
        }
      },
      {
        "date": "2023-07-05",
        "tokens": {
          "CRV": { "added": "33849.801066416843778", "removed": "0" },
          "cvxCRV": { "added": "0", "removed": "0" }
        }
      },
      {
        "date": "2023-07-06",
        "tokens": {
          "CRV": { "added": "156840.0032182609843", "removed": "0" },
          "cvxCRV": { "added": "0", "removed": "0" }
        }
      },
      {
        "date": "2023-07-07",
        "tokens": {
          "CRV": { "added": "8810.5329724583926605", "removed": "0" },
          "cvxCRV": {
            "added": "10337.300224959575107",
            "removed": "13011.605337154041348"
          }
        }
      },
      {
        "date": "2023-07-08",
        "tokens": {
          "CRV": {
            "added": "78685.99703120338404",
            "removed": "353.07301019448880802"
          },
          "cvxCRV": { "added": "0", "removed": "0" }
        }
      },
      {
        "date": "2023-07-09",
        "tokens": {
          "CRV": { "added": "10050.923644664972884", "removed": "0" },
          "cvxCRV": { "added": "234158.59062567771262", "removed": "0" }
        }
      }
    ],
    "tokensSummary": [
      {
        "symbol": "CRV",
        "totalAdded": "391817.91393865766006",
        "totalRemoved": "353.07301019448880802",
        "tvlBefore": "16058503.525716457089",
        "tvlNow": "16449968.36664492026",
        "tvlPercentChange": "0.024377417254451036875"
      },
      {
        "symbol": "cvxCRV",
        "totalAdded": "585996.78236643779412",
        "totalRemoved": "13011.605337154041348",
        "tvlBefore": "38532300.720838479986",
        "tvlNow": "39105285.897867763739",
        "tvlPercentChange": "0.014870256027027480879"
      }
    ]
  },
  "0xa5407eae9ba41422680e2e00537571bcc53efbfd": {
    "graph": [
      {
        "date": "2023-07-04",
        "tokens": {
          "DAI": { "added": "4315.9744072187476014", "removed": "0" },
          "USDC": { "added": "0", "removed": "0" },
          "USDT": { "added": "0", "removed": "0" },
          "sUSD": { "added": "0", "removed": "0" }
        }
      },
      {
        "date": "2023-07-08",
        "tokens": {
          "DAI": { "added": "0", "removed": "0" },
          "USDC": { "added": "0", "removed": "0" },
          "USDT": { "added": "0", "removed": "0" },
          "sUSD": { "added": "0", "removed": "0" }
        }
      }
    ],
    "tokensSummary": [
      {
        "symbol": "DAI",
        "totalAdded": "4315.9744072187476014",
        "totalRemoved": "0",
        "tvlBefore": "13646803.219925006462",
        "tvlNow": "13651119.19433222521",
        "tvlPercentChange": "0.0003162626688217510369"
      },
      {
        "symbol": "USDC",
        "totalAdded": "0",
        "totalRemoved": "0",
        "tvlBefore": "13554665.0618596074",
        "tvlNow": "13554665.0618596074",
        "tvlPercentChange": "0"
      },
      {
        "symbol": "USDT",
        "totalAdded": "0",
        "totalRemoved": "0",
        "tvlBefore": "13621071.116529",
        "tvlNow": "13621071.116529",
        "tvlPercentChange": "0"
      },
      {
        "symbol": "sUSD",
        "totalAdded": "0",
        "totalRemoved": "0",
        "tvlBefore": "13937916.335849064597",
        "tvlNow": "13937916.335849064597",
        "tvlPercentChange": "0"
      }
    ]
  },
  "0x8301ae4fc9c624d1d396cbdaa1ed877821d7c511": {
    "graph": [
      {
        "date": "2023-07-02",
        "tokens": {
          "WETH": { "added": "0", "removed": "121462.25" },
          "CRV": { "added": "0", "removed": "0" }
        }
      },
      {
        "date": "2023-07-03",
        "tokens": {
          "WETH": {
            "added": "6571.5172359640568363",
            "removed": "42473.3452154200413"
          },
          "CRV": { "added": "7365.0335108727253664", "removed": "0" }
        }
      },
      {
        "date": "2023-07-04",
        "tokens": {
          "WETH": {
            "added": "96570.594967907624259",
            "removed": "3176.8387529785271078"
          },
          "CRV": { "added": "96450.44998310495203", "removed": "0" }
        }
      },
      {
        "date": "2023-07-05",
        "tokens": {
          "WETH": { "added": "5100.0016802689271008", "removed": "0" },
          "CRV": { "added": "5111.3060510696057691", "removed": "0" }
        }
      },
      {
        "date": "2023-07-06",
        "tokens": {
          "WETH": {
            "added": "16025.691034228009952",
            "removed": "761508.42981510568999"
          },
          "CRV": {
            "added": "16229.949068396949188",
            "removed": "1886.6980430564860007"
          }
        }
      },
      {
        "date": "2023-07-07",
        "tokens": {
          "WETH": { "added": "0", "removed": "45938.722320860258999" },
          "CRV": { "added": "730.34324988790640916", "removed": "0" }
        }
      },
      {
        "date": "2023-07-08",
        "tokens": {
          "WETH": { "added": "30441.927599842701113", "removed": "0" },
          "CRV": { "added": "226414.89486087162173", "removed": "0" }
        }
      },
      {
        "date": "2023-07-09",
        "tokens": {
          "WETH": { "added": "213.6483742347507824", "removed": "0" },
          "CRV": { "added": "209.03442470747087771", "removed": "0" }
        }
      }
    ],
    "tokensSummary": [
      {
        "symbol": "WETH",
        "totalAdded": "154923.38089244607004",
        "totalRemoved": "974559.5861043645174",
        "tvlBefore": "28116017.434590443932",
        "tvlNow": "27296381.229378525485",
        "tvlPercentChange": "-0.029151931176552060539"
      },
      {
        "symbol": "CRV",
        "totalAdded": "352511.01114891123137",
        "totalRemoved": "1886.6980430564860007",
        "tvlBefore": "26379553.325236432842",
        "tvlNow": "26730177.638342287587",
        "tvlPercentChange": "0.013291518199075199602"
      }
    ]
  },
  "0x94b17476a93b3262d87b9a326965d1e91f9c13e7": {
    "graph": [
      {
        "date": "2023-07-02",
        "tokens": {
          "ETH": { "added": "130748.1186783", "removed": "0" },
          "OETH": { "added": "0", "removed": "0" }
        }
      },
      {
        "date": "2023-07-03",
        "tokens": {
          "ETH": { "added": "4669.575", "removed": "115754.60583905506551" },
          "OETH": { "added": "0", "removed": "0" }
        }
      },
      {
        "date": "2023-07-04",
        "tokens": {
          "ETH": { "added": "623855.406783", "removed": "0" },
          "OETH": { "added": "0", "removed": "0" }
        }
      },
      {
        "date": "2023-07-05",
        "tokens": {
          "ETH": { "added": "0", "removed": "0" },
          "OETH": { "added": "65500.124207401036684", "removed": "0" }
        }
      },
      {
        "date": "2023-07-06",
        "tokens": {
          "ETH": { "added": "0", "removed": "89926.710679156905424" },
          "OETH": { "added": "0", "removed": "0" }
        }
      },
      {
        "date": "2023-07-07",
        "tokens": {
          "ETH": { "added": "0", "removed": "8311.7995351813718662" },
          "OETH": { "added": "0", "removed": "0" }
        }
      },
      {
        "date": "2023-07-08",
        "tokens": {
          "ETH": { "added": "0", "removed": "56447.590706959387905" },
          "OETH": { "added": "3782.5063245172114578", "removed": "0" }
        }
      },
      {
        "date": "2023-07-09",
        "tokens": {
          "ETH": { "added": "1867.8673566", "removed": "0" },
          "OETH": { "added": "0", "removed": "2206.4203994891242688" }
        }
      }
    ],
    "tokensSummary": [
      {
        "symbol": "ETH",
        "totalAdded": "761140.9678179",
        "totalRemoved": "270440.70676035273071",
        "tvlBefore": "25380830.677816969127",
        "tvlNow": "25871530.938874516396",
        "tvlPercentChange": "0.019333498863235507543"
      },
      {
        "symbol": "OETH",
        "totalAdded": "69282.630531918248142",
        "totalRemoved": "2206.4203994891242688",
        "tvlBefore": "26039187.330599867531",
        "tvlNow": "26106263.540732296655",
        "tvlPercentChange": "0.0025759717183494713237"
      }
    ]
  },
  "0x960ea3e3c7fb317332d990873d354e18d7645590": {
    "graph": [
      {
        "date": "2023-07-02",
        "tokens": {
          "USDT": { "added": "2436.975027", "removed": "0" },
          "WBTC": { "added": "2415.1860104", "removed": "0" },
          "WETH": { "added": "2373.2239608275319886", "removed": "0" }
        }
      },
      {
        "date": "2023-07-03",
        "tokens": {
          "USDT": { "added": "0", "removed": "0.164265585623631542" },
          "WBTC": { "added": "0", "removed": "0" },
          "WETH": {
            "added": "2.3567645053797260819",
            "removed": "56.577545833158186842"
          }
        }
      },
      {
        "date": "2023-07-04",
        "tokens": {
          "USDT": { "added": "0", "removed": "0.09513295107550442" },
          "WBTC": { "added": "0", "removed": "0" },
          "WETH": {
            "added": "443.43895800160161214",
            "removed": "1876.4842490709827764"
          }
        }
      },
      {
        "date": "2023-07-05",
        "tokens": {
          "USDT": { "added": "160.750276", "removed": "0" },
          "WBTC": { "added": "158.43549052", "removed": "0" },
          "WETH": { "added": "3417.0526990455905837", "removed": "0" }
        }
      },
      {
        "date": "2023-07-06",
        "tokens": {
          "USDT": { "added": "748.144335", "removed": "0.820771770621976185" },
          "WBTC": { "added": "1394.68267566", "removed": "0" },
          "WETH": { "added": "0.99366071360015181085", "removed": "0" }
        }
      },
      {
        "date": "2023-07-07",
        "tokens": {
          "USDT": { "added": "0", "removed": "0" },
          "WBTC": { "added": "0", "removed": "0" },
          "WETH": { "added": "0", "removed": "10.309786854289358995" }
        }
      },
      {
        "date": "2023-07-08",
        "tokens": {
          "USDT": { "added": "0", "removed": "0.085880479019021063" },
          "WBTC": { "added": "0", "removed": "0" },
          "WETH": { "added": "0", "removed": "104.08563075884820071" }
        }
      },
      {
        "date": "2023-07-09",
        "tokens": {
          "USDT": { "added": "0", "removed": "0" },
          "WBTC": { "added": "0", "removed": "0" },
          "WETH": { "added": "0", "removed": "801.22430884549793309" }
        }
      }
    ],
    "tokensSummary": [
      {
        "symbol": "USDT",
        "totalAdded": "3345.869638",
        "totalRemoved": "1.16605078634013321",
        "tvlBefore": "15679066.42180378634",
        "tvlNow": "15682411.125391",
        "tvlPercentChange": "0.00021332287887768710052"
      },
      {
        "symbol": "WBTC",
        "totalAdded": "3968.30417658",
        "totalRemoved": "0",
        "tvlBefore": "15640359.93792386",
        "tvlNow": "15644328.24210044",
        "tvlPercentChange": "0.00025372204938569735343"
      },
      {
        "symbol": "WETH",
        "totalAdded": "6237.0660430937040623",
        "totalRemoved": "2848.681521362776456",
        "tvlBefore": "15596523.54330509608",
        "tvlNow": "15599911.927826827008",
        "tvlPercentChange": "0.00021725255069328657881"
      }
    ]
  },
  "0xc4c319e2d4d66cca4464c0c2b32c9bd23ebe784e": {
    "graph": [
      {
        "date": "2023-07-02",
        "tokens": {
          "ETH": { "added": "130748.1186783", "removed": "0" },
          "alETH": { "added": "0", "removed": "0" }
        }
      },
      {
        "date": "2023-07-04",
        "tokens": {
          "ETH": { "added": "0.186783", "removed": "0" },
          "alETH": { "added": "0", "removed": "0" }
        }
      },
      {
        "date": "2023-07-05",
        "tokens": {
          "ETH": { "added": "7471.32", "removed": "0" },
          "alETH": { "added": "0", "removed": "0" }
        }
      },
      {
        "date": "2023-07-06",
        "tokens": {
          "ETH": { "added": "0", "removed": "0" },
          "alETH": { "added": "0", "removed": "0" }
        }
      },
      {
        "date": "2023-07-07",
        "tokens": {
          "ETH": { "added": "0", "removed": "0" },
          "alETH": { "added": "74150.850652661155854", "removed": "0" }
        }
      },
      {
        "date": "2023-07-08",
        "tokens": {
          "ETH": { "added": "104598.48", "removed": "526728.06" },
          "alETH": { "added": "215784.60951129882679", "removed": "0" }
        }
      },
      {
        "date": "2023-07-09",
        "tokens": {
          "ETH": { "added": "0.0373566", "removed": "0" },
          "alETH": { "added": "0", "removed": "0" }
        }
      }
    ],
    "tokensSummary": [
      {
        "symbol": "ETH",
        "totalAdded": "242818.1428179",
        "totalRemoved": "526728.06",
        "tvlBefore": "16016798.281206091419",
        "tvlNow": "15732888.364023991419",
        "tvlPercentChange": "-0.017725759680399815421"
      },
      {
        "symbol": "alETH",
        "totalAdded": "289935.46016395998264",
        "totalRemoved": "0",
        "tvlBefore": "30024313.092035643644",
        "tvlNow": "30314248.552199603627",
        "tvlPercentChange": "0.0096566892063508789168"
      }
    ]
  },
  "0xc5424b857f758e906013f3555dad202e4bdb4567": {
    "graph": [
      {
        "date": "2023-07-02",
        "tokens": {
          "ETH": { "added": "0.0186783", "removed": "0" },
          "sETH": { "added": "0", "removed": "0" }
        }
      },
      {
        "date": "2023-07-04",
        "tokens": {
          "ETH": { "added": "0", "removed": "830276.33716950044248" },
          "sETH": { "added": "0", "removed": "0" }
        }
      },
      {
        "date": "2023-07-06",
        "tokens": {
          "ETH": { "added": "0", "removed": "1210.2705791958480182" },
          "sETH": { "added": "0", "removed": "0" }
        }
      },
      {
        "date": "2023-07-07",
        "tokens": {
          "ETH": { "added": "0", "removed": "83398.485408536787476" },
          "sETH": { "added": "0", "removed": "0" }
        }
      },
      {
        "date": "2023-07-09",
        "tokens": {
          "ETH": { "added": "0.0373566", "removed": "0" },
          "sETH": { "added": "0", "removed": "0" }
        }
      }
    ],
    "tokensSummary": [
      {
        "symbol": "ETH",
        "totalAdded": "0.0560349",
        "totalRemoved": "914885.09315723307797",
        "tvlBefore": "15281016.474773968834",
        "tvlNow": "14366131.437651635756",
        "tvlPercentChange": "-0.059870692413206479474"
      },
      {
        "symbol": "sETH",
        "totalAdded": "0",
        "totalRemoved": "0",
        "tvlBefore": "15374249.324799865357",
        "tvlNow": "15374249.324799865357",
        "tvlPercentChange": "0"
      }
    ]
  },
  "0x828b154032950c8ff7cf8085d841723db2696056": {
    "graph": [
      {
        "date": "2023-07-02",
        "tokens": {
          "WETH": { "added": "2379.7892463049734203", "removed": "0" },
          "stETH": { "added": "3547.7216857187428081", "removed": "0" }
        }
      },
      {
        "date": "2023-07-03",
        "tokens": {
          "WETH": { "added": "0", "removed": "0" },
          "stETH": { "added": "43319.54900456570168", "removed": "0" }
        }
      },
      {
        "date": "2023-07-04",
        "tokens": {
          "WETH": { "added": "0", "removed": "0" },
          "stETH": { "added": "0", "removed": "252217.74290528301659" }
        }
      }
    ],
    "tokensSummary": [
      {
        "symbol": "WETH",
        "totalAdded": "2379.7892463049734203",
        "totalRemoved": "0",
        "tvlBefore": "12116439.293893310627",
        "tvlNow": "12118819.0831396156",
        "tvlPercentChange": "0.00019640995085943999733"
      },
      {
        "symbol": "stETH",
        "totalAdded": "46867.270690284444488",
        "totalRemoved": "252217.74290528301659",
        "tvlBefore": "17233405.309759059",
        "tvlNow": "17028054.837544060428",
        "tvlPercentChange": "-0.011915838368793612852"
      }
    ]
  },
  "0xb576491f1e6e5e62f1d8f26062ee822b40b0e0d4": {
    "graph": [
      {
        "date": "2023-07-03",
        "tokens": {
          "WETH": {
            "added": "893.06257102514960431",
            "removed": "161187.35686541191737"
          },
          "CVX": { "added": "964.30804056902525467", "removed": "0" }
        }
      },
      {
        "date": "2023-07-04",
        "tokens": {
          "WETH": { "added": "0", "removed": "0" },
          "CVX": { "added": "0", "removed": "183.41583454190351687" }
        }
      },
      {
        "date": "2023-07-05",
        "tokens": {
          "WETH": { "added": "693.34623089621732215", "removed": "0" },
          "CVX": { "added": "996.03503559184473358", "removed": "0" }
        }
      },
      {
        "date": "2023-07-07",
        "tokens": {
          "WETH": { "added": "0", "removed": "0" },
          "CVX": { "added": "0", "removed": "0" }
        }
      },
      {
        "date": "2023-07-08",
        "tokens": {
          "WETH": { "added": "1085.4263643854451014", "removed": "0" },
          "CVX": { "added": "1055.3772701835727913", "removed": "0" }
        }
      },
      {
        "date": "2023-07-09",
        "tokens": {
          "WETH": { "added": "0", "removed": "0" },
          "CVX": { "added": "389.7665255857934193", "removed": "0" }
        }
      }
    ],
    "tokensSummary": [
      {
        "symbol": "WETH",
        "totalAdded": "2671.8351663068120279",
        "totalRemoved": "161187.35686541191737",
        "tvlBefore": "14190541.850098648787",
        "tvlNow": "14032026.328399543682",
        "tvlPercentChange": "-0.011170505212103873836"
      },
      {
        "symbol": "CVX",
        "totalAdded": "3405.4868719302361989",
        "totalRemoved": "183.41583454190351687",
        "tvlBefore": "13709605.574187813384",
        "tvlNow": "13712827.645225201717",
        "tvlPercentChange": "0.00023502288376952197187"
      }
    ]
  },
  "0x445fe580ef8d70ff569ab36e80c647af338db351": {
    "graph": [
      {
        "date": "2023-07-02",
        "tokens": {
          "amDAI": {
            "added": "0.999389046024",
            "removed": "1.7502059602219030746"
          },
          "amUSDC": { "added": "0.999912", "removed": "8005.4988967144969705" },
          "amUSDT": { "added": "0", "removed": "2403.0161909863718851" }
        }
      },
      {
        "date": "2023-07-03",
        "tokens": {
          "amDAI": { "added": "0", "removed": "199223.04830201624645" },
          "amUSDC": {
            "added": "60861.9936732",
            "removed": "288.04032335214265107"
          },
          "amUSDT": {
            "added": "0.009996150261360001",
            "removed": "180903.90059392866034"
          }
        }
      },
      {
        "date": "2023-07-04",
        "tokens": {
          "amDAI": { "added": "0", "removed": "0" },
          "amUSDC": { "added": "0.999912", "removed": "5569.3605288199002346" },
          "amUSDT": { "added": "0", "removed": "7952.8433277863569201" }
        }
      },
      {
        "date": "2023-07-05",
        "tokens": {
          "amDAI": {
            "added": "4.9979670654529639607",
            "removed": "1480.0238256630998352"
          },
          "amUSDC": {
            "added": "11.00980105224",
            "removed": "595.3612686391632499"
          },
          "amUSDT": {
            "added": "1004.8682679963267065",
            "removed": "4.348325363691600435"
          }
        }
      },
      {
        "date": "2023-07-06",
        "tokens": {
          "amDAI": {
            "added": "5.996334276144",
            "removed": "2.8226635439369270876"
          },
          "amUSDC": { "added": "6.999384", "removed": "39164.209602371334874" },
          "amUSDT": {
            "added": "8.9965352352240009",
            "removed": "0.93844146380120302562"
          }
        }
      },
      {
        "date": "2023-07-07",
        "tokens": {
          "amDAI": { "added": "0", "removed": "38.183520090553748972" },
          "amUSDC": {
            "added": "56273.570283994128",
            "removed": "30782.85724469168324"
          },
          "amUSDT": {
            "added": "136.29973395669179237",
            "removed": "6705.2884751341636754"
          }
        }
      },
      {
        "date": "2023-07-08",
        "tokens": {
          "amDAI": {
            "added": "0.39866383868709404409",
            "removed": "3.6534338594052160761"
          },
          "amUSDC": {
            "added": "1007.04348737388",
            "removed": "346.38849889296516933"
          },
          "amUSDT": {
            "added": "1009.2954210017493397",
            "removed": "1699.0167471470670264"
          }
        }
      },
      {
        "date": "2023-07-09",
        "tokens": {
          "amDAI": {
            "added": "0.81949901773968",
            "removed": "1.6681358469706348241"
          },
          "amUSDC": { "added": "1.05990672", "removed": "0" },
          "amUSDT": { "added": "0.009996150261360001", "removed": "0" }
        }
      }
    ],
    "tokensSummary": [
      {
        "symbol": "amDAI",
        "totalAdded": "13.211853244047738005",
        "totalRemoved": "200751.15008698043472",
        "tvlBefore": "10795666.824827496345",
        "tvlNow": "10594928.886593759958",
        "tvlPercentChange": "-0.018594306538998249683"
      },
      {
        "symbol": "amUSDC",
        "totalAdded": "118163.676360340248",
        "totalRemoved": "84751.716363481686389",
        "tvlBefore": "6898525.2043240354624",
        "tvlNow": "6931937.164320894024",
        "tvlPercentChange": "0.0048433482530317859819"
      },
      {
        "symbol": "amUSDT",
        "totalAdded": "2159.4799504905145595",
        "totalRemoved": "199669.35210181011265",
        "tvlBefore": "7084576.6747657175134",
        "tvlNow": "6887066.8026143979153",
        "tvlPercentChange": "-0.027878853066100964335"
      }
    ]
  },
  "0x9848482da3ee3076165ce6497eda906e66bb85c5": {
    "graph": [
      {
        "date": "2023-07-02",
        "tokens": {
          "ETH": { "added": "0.0186783", "removed": "0" },
          "pETH": {
            "added": "82756.471007826907004",
            "removed": "318277.25700542123417"
          }
        }
      },
      {
        "date": "2023-07-03",
        "tokens": {
          "ETH": { "added": "9339.15", "removed": "893849.10856212083418" },
          "pETH": {
            "added": "59913.481178726051228",
            "removed": "8942.2633638675122146"
          }
        }
      },
      {
        "date": "2023-07-04",
        "tokens": {
          "ETH": {
            "added": "204919.816083",
            "removed": "14667.662331760286752"
          },
          "pETH": {
            "added": "204680.03163349737922",
            "removed": "141869.00826775808129"
          }
        }
      },
      {
        "date": "2023-07-05",
        "tokens": {
          "ETH": { "added": "42399.741", "removed": "41569.698025750381001" },
          "pETH": { "added": "24800.878310498096377", "removed": "0" }
        }
      },
      {
        "date": "2023-07-06",
        "tokens": {
          "ETH": { "added": "0", "removed": "0" },
          "pETH": { "added": "0", "removed": "0" }
        }
      },
      {
        "date": "2023-07-07",
        "tokens": {
          "ETH": { "added": "0", "removed": "191038.31497674801121" },
          "pETH": { "added": "0", "removed": "0" }
        }
      },
      {
        "date": "2023-07-08",
        "tokens": {
          "ETH": { "added": "522992.4", "removed": "0" },
          "pETH": { "added": "0", "removed": "0" }
        }
      }
    ],
    "tokensSummary": [
      {
        "symbol": "ETH",
        "totalAdded": "779651.1257613",
        "totalRemoved": "1141124.7838963795131",
        "tvlBefore": "11779783.604698724287",
        "tvlNow": "11418309.946563644774",
        "tvlPercentChange": "-0.030685933652541356641"
      },
      {
        "symbol": "pETH",
        "totalAdded": "372150.86213054843383",
        "totalRemoved": "469088.52863704682767",
        "tvlBefore": "9527223.8178087043535",
        "tvlNow": "9430286.1513022059597",
        "tvlPercentChange": "-0.010174807305911955027"
      }
    ]
  },
  "0xa138341185a9d0429b0021a11fb717b225e13e1f": {
    "graph": [
      {
        "date": "2023-07-03",
        "tokens": {
          "USDR": { "added": "0", "removed": "0" },
          "am3CRV": { "added": "0", "removed": "0" }
        }
      },
      {
        "date": "2023-07-04",
        "tokens": {
          "USDR": { "added": "0", "removed": "0" },
          "am3CRV": { "added": "0", "removed": "15853.212708852290771" }
        }
      },
      {
        "date": "2023-07-07",
        "tokens": {
          "USDR": { "added": "0", "removed": "0" },
          "am3CRV": { "added": "0", "removed": "0" }
        }
      }
    ],
    "tokensSummary": [
      {
        "symbol": "USDR",
        "totalAdded": "0",
        "totalRemoved": "0",
        "tvlBefore": "10948801.164765220347",
        "tvlNow": "10948801.164765220347",
        "tvlPercentChange": "0"
      },
      {
        "symbol": "am3CRV",
        "totalAdded": "0",
        "totalRemoved": "15853.212708852290771",
        "tvlBefore": "9688707.055340274648",
        "tvlNow": "9672853.8426314223572",
        "tvlPercentChange": "-0.0016362567903334666461"
      }
    ]
  },
  "0x7f90122bf0700f9e7e1f688fe926940e8839f353": {
    "graph": [
      {
        "date": "2023-07-02",
        "tokens": {
          "USDC": {
            "added": "3138.6788337267",
            "removed": "152.14975105589083555"
          },
          "USDT": {
            "added": "31616.532896",
            "removed": "1403.1473134469881664"
          }
        }
      },
      {
        "date": "2023-07-03",
        "tokens": {
          "USDC": {
            "added": "13764.9436849683",
            "removed": "458.98976690562506398"
          },
          "USDT": { "added": "14324.30276", "removed": "59.949905683225669213" }
        }
      },
      {
        "date": "2023-07-04",
        "tokens": {
          "USDC": {
            "added": "1017.3247063551",
            "removed": "80.578569961730269527"
          },
          "USDT": { "added": "1.993582", "removed": "0" }
        }
      },
      {
        "date": "2023-07-05",
        "tokens": {
          "USDC": { "added": "0", "removed": "1055.51594441880711" },
          "USDT": { "added": "9", "removed": "72.531894077470435519" }
        }
      },
      {
        "date": "2023-07-06",
        "tokens": {
          "USDC": {
            "added": "1009.4140514997",
            "removed": "44.253196706068266992"
          },
          "USDT": { "added": "10.029915", "removed": "1380.4616493285104602" }
        }
      },
      {
        "date": "2023-07-07",
        "tokens": {
          "USDC": {
            "added": "8358.8359358097",
            "removed": "198945.10498222956382"
          },
          "USDT": {
            "added": "201264.741044",
            "removed": "232.99223202666370584"
          }
        }
      },
      {
        "date": "2023-07-08",
        "tokens": {
          "USDC": {
            "added": "6007.191980724",
            "removed": "5637.3404666073958792"
          },
          "USDT": { "added": "1703.928657", "removed": "280.1695757106875317" }
        }
      },
      {
        "date": "2023-07-09",
        "tokens": {
          "USDC": {
            "added": "2134.8035972901",
            "removed": "3.3970651807210515588"
          },
          "USDT": { "added": "400295.641554", "removed": "0" }
        }
      }
    ],
    "tokensSummary": [
      {
        "symbol": "USDC",
        "totalAdded": "35431.1927903736",
        "totalRemoved": "206377.3297430658023",
        "tvlBefore": "9363544.1627489388023",
        "tvlNow": "9192598.0257962466",
        "tvlPercentChange": "-0.018256563324896630485"
      },
      {
        "symbol": "USDT",
        "totalAdded": "649226.170408",
        "totalRemoved": "3429.2525702735459689",
        "tvlBefore": "7178315.008192273546",
        "tvlNow": "7824111.92603",
        "tvlPercentChange": "0.089964973270288192063"
      }
    ]
  },
  "0x98a7f18d4e56cfe84e3d081b40001b3d5bd3eb8b": {
    "graph": [
      {
        "date": "2023-07-03",
        "tokens": {
          "USDC": { "added": "0", "removed": "46294.637498821306924" },
          "EURS": { "added": "0", "removed": "0" }
        }
      }
    ],
    "tokensSummary": [
      {
        "symbol": "USDC",
        "totalAdded": "0",
        "totalRemoved": "46294.637498821306924",
        "tvlBefore": "7804973.0148315448069",
        "tvlNow": "7758678.3773327235",
        "tvlPercentChange": "-0.0059314282587331260354"
      },
      {
        "symbol": "EURS",
        "totalAdded": "0",
        "totalRemoved": "0",
        "tvlBefore": "7480034.33459",
        "tvlNow": "7480034.33459",
        "tvlPercentChange": "0"
      }
    ]
  },
  "0xe57180685e3348589e9521aa53af0bcd497e884d": {
    "graph": [
      {
        "date": "2023-07-05",
        "tokens": {
          "DOLA": { "added": "0", "removed": "0" },
          "FRAXBP": { "added": "444418.71353586721976", "removed": "0" }
        }
      }
    ],
    "tokensSummary": [
      {
        "symbol": "DOLA",
        "totalAdded": "0",
        "totalRemoved": "0",
        "tvlBefore": "8493306.704728468342",
        "tvlNow": "8493306.704728468342",
        "tvlPercentChange": "0"
      },
      {
        "symbol": "FRAXBP",
        "totalAdded": "444418.71353586721976",
        "totalRemoved": "0",
        "tvlBefore": "6072180.3426616082145",
        "tvlNow": "6516599.0561974754343",
        "tvlPercentChange": "0.073189313962481216515"
      }
    ]
  },
  "0xf253f83aca21aabd2a20553ae0bf7f65c755a07f": {
    "graph": [
      {
        "date": "2023-07-02",
        "tokens": {
          "WBTC": { "added": "30262", "removed": "0" },
          "sBTC": { "added": "0", "removed": "0" }
        }
      },
      {
        "date": "2023-07-04",
        "tokens": {
          "WBTC": { "added": "0", "removed": "8212.4801683841778601" },
          "sBTC": { "added": "4389.597162619905361", "removed": "0" }
        }
      },
      {
        "date": "2023-07-07",
        "tokens": {
          "WBTC": { "added": "26874.91566354", "removed": "0" },
          "sBTC": { "added": "0", "removed": "0" }
        }
      },
      {
        "date": "2023-07-08",
        "tokens": {
          "WBTC": { "added": "0", "removed": "0" },
          "sBTC": { "added": "0", "removed": "269671.06555725639971" }
        }
      },
      {
        "date": "2023-07-09",
        "tokens": {
          "WBTC": { "added": "69154.79381832", "removed": "0" },
          "sBTC": { "added": "0", "removed": "0" }
        }
      }
    ],
    "tokensSummary": [
      {
        "symbol": "WBTC",
        "totalAdded": "126291.70948186",
        "totalRemoved": "8212.4801683841778601",
        "tvlBefore": "7414738.0576244441779",
        "tvlNow": "7532817.28693792",
        "tvlPercentChange": "0.015924936038982123749"
      },
      {
        "symbol": "sBTC",
        "totalAdded": "4389.597162619905361",
        "totalRemoved": "269671.06555725639971",
        "tvlBefore": "7494363.3447945755825",
        "tvlNow": "7229081.8763999390881",
        "tvlPercentChange": "-0.035397465560419528624"
      }
    ]
  },
  "0x061b87122ed14b9526a813209c8a59a633257bab": {
    "graph": [
      {
        "date": "2023-07-03",
        "tokens": {
          "sUSD": { "added": "0.0000019991604414049211742", "removed": "0" },
          "3CRV": { "added": "0", "removed": "0" }
        }
      },
      {
        "date": "2023-07-04",
        "tokens": {
          "sUSD": {
            "added": "0.99918866428105202058",
            "removed": "0.98261091121809161051"
          },
          "3CRV": { "added": "0", "removed": "0" }
        }
      },
      {
        "date": "2023-07-05",
        "tokens": {
          "sUSD": { "added": "0.099952425438188141158", "removed": "0" },
          "3CRV": { "added": "0", "removed": "0" }
        }
      },
      {
        "date": "2023-07-06",
        "tokens": {
          "sUSD": { "added": "1.2391610715183355394", "removed": "0" },
          "3CRV": { "added": "0.011035689260977754678", "removed": "0" }
        }
      },
      {
        "date": "2023-07-07",
        "tokens": {
          "sUSD": { "added": "0", "removed": "0.0009824128278444802591" },
          "3CRV": { "added": "0", "removed": "0" }
        }
      }
    ],
    "tokensSummary": [
      {
        "symbol": "sUSD",
        "totalAdded": "2.3383041603980171061",
        "totalRemoved": "0.98359332404593609077",
        "tvlBefore": "9445409.045486633638",
        "tvlNow": "9445410.4001974699901",
        "tvlPercentChange": "1.4342532227330387825e-7"
      },
      {
        "symbol": "3CRV",
        "totalAdded": "0.011035689260977754678",
        "totalRemoved": "0",
        "tvlBefore": "5283726.2658671132774",
        "tvlNow": "5283726.2769028025384",
        "tvlPercentChange": "2.0886186576868268232e-9"
      }
    ]
  },
  "0xb90b9b1f91a01ea22a182cd84c1e22222e39b415": {
    "graph": [
      {
        "date": "2023-07-02",
        "tokens": {
          "ETH": { "added": "9.33835", "removed": "108974.46981101618685" },
          "wstETH": { "added": "0", "removed": "0" }
        }
      },
      {
        "date": "2023-07-03",
        "tokens": {
          "ETH": { "added": "17597.18674", "removed": "88875.709163007834493" },
          "wstETH": { "added": "0", "removed": "4576.3632338317174928" }
        }
      },
      {
        "date": "2023-07-04",
        "tokens": {
          "ETH": {
            "added": "22460.3827142499",
            "removed": "69248.086867528777532"
          },
          "wstETH": {
            "added": "9492.1983061159225618",
            "removed": "246.86384758926110836"
          }
        }
      },
      {
        "date": "2023-07-05",
        "tokens": {
          "ETH": { "added": "3735.34", "removed": "5687.3441958528294984" },
          "wstETH": { "added": "3545.3233699170794233", "removed": "0" }
        }
      },
      {
        "date": "2023-07-06",
        "tokens": {
          "ETH": { "added": "8408.196426015834198", "removed": "0" },
          "wstETH": { "added": "7764.3970931261278891", "removed": "0" }
        }
      },
      {
        "date": "2023-07-07",
        "tokens": {
          "ETH": {
            "added": "3640.9549485132690223",
            "removed": "91130.888586209819495"
          },
          "wstETH": { "added": "3618.0312685411575047", "removed": "0" }
        }
      },
      {
        "date": "2023-07-08",
        "tokens": {
          "ETH": {
            "added": "1873.5683498658607046",
            "removed": "40009.194022705361922"
          },
          "wstETH": { "added": "5780.8897755424705984", "removed": "0" }
        }
      },
      {
        "date": "2023-07-09",
        "tokens": {
          "ETH": { "added": "0", "removed": "787211.3292571126342" },
          "wstETH": { "added": "0", "removed": "611.33500797297114713" }
        }
      }
    ],
    "tokensSummary": [
      {
        "symbol": "ETH",
        "totalAdded": "57724.967528644863925",
        "totalRemoved": "1191137.021903433444",
        "tvlBefore": "8283432.2612835851718",
        "tvlNow": "7150020.2069087965917",
        "tvlPercentChange": "-0.13682879495161793812"
      },
      {
        "symbol": "wstETH",
        "totalAdded": "30200.839813242757977",
        "totalRemoved": "5434.5620893939497483",
        "tvlBefore": "7508235.8550811183171",
        "tvlNow": "7533002.1328049671253",
        "tvlPercentChange": "0.0032985481812067071144"
      }
    ]
  },
  "0x4d9f9d15101eec665f77210cb999639f760f831e": {
    "graph": [
      {
        "date": "2023-07-02",
        "tokens": {
          "stETH": { "added": "0", "removed": "186469.78536784838668" },
          "frxETH": { "added": "0", "removed": "0" }
        }
      },
      {
        "date": "2023-07-04",
        "tokens": {
          "stETH": { "added": "0", "removed": "188845.80308026044854" },
          "frxETH": { "added": "0", "removed": "0" }
        }
      },
      {
        "date": "2023-07-06",
        "tokens": {
          "stETH": { "added": "0", "removed": "0" },
          "frxETH": { "added": "0", "removed": "356129.39189469257447" }
        }
      },
      {
        "date": "2023-07-08",
        "tokens": {
          "stETH": { "added": "64246.00377038095881", "removed": "0" },
          "frxETH": { "added": "61595.8488568079316", "removed": "0" }
        }
      }
    ],
    "tokensSummary": [
      {
        "symbol": "stETH",
        "totalAdded": "64246.00377038095881",
        "totalRemoved": "375315.58844810883522",
        "tvlBefore": "7084246.0499224977412",
        "tvlNow": "6773176.4652447698648",
        "tvlPercentChange": "-0.043910048082128796798"
      },
      {
        "symbol": "frxETH",
        "totalAdded": "61595.8488568079316",
        "totalRemoved": "356129.39189469257447",
        "tvlBefore": "7779654.4030772134634",
        "tvlNow": "7485120.8600393288205",
        "tvlPercentChange": "-0.037859463644218307648"
      }
    ]
  },
  "0xaeda92e6a3b1028edc139a4ae56ec881f3064d4f": {
    "graph": [
      {
        "date": "2023-07-05",
        "tokens": {
          "eUSD": { "added": "0", "removed": "0" },
          "FRAXBP": { "added": "0", "removed": "444503.65575680735011" }
        }
      }
    ],
    "tokensSummary": [
      {
        "symbol": "eUSD",
        "totalAdded": "0",
        "totalRemoved": "0",
        "tvlBefore": "5713340.9448713366312",
        "tvlNow": "5713340.9448713366312",
        "tvlPercentChange": "0"
      },
      {
        "symbol": "FRAXBP",
        "totalAdded": "0",
        "totalRemoved": "444503.65575680735011",
        "tvlBefore": "8129410.1427124458644",
        "tvlNow": "7684906.4869556385143",
        "tvlPercentChange": "-0.054678463499012854321"
      }
    ]
  }
}
